[{"arguments":["clang","-Wno-documentation-unknown-command","-Wno-unknown-warning-option","-Wno-unknown-pragmas","-nostdinc","-nostdinc++","-g","-std=gnu++1z","-Wall","-Wextra","-Wextra","-fexceptions","-mthreads","-fsyntax-only","-m64","--target=x86_64-w64-mingw32","-DUNICODE","-D_UNICODE","-DWIN32","-DMINGW_HAS_SECURE_API","-DQT_QML_DEBUG","-DQT_WIDGETS_LIB","-DQT_GUI_LIB","-DQT_CORE_LIB","-DQT_NEEDS_QMAIN","-DQ_CREATOR_RUN","-DQT_ANNOTATE_FUNCTION(x)=__attribute__((annotate(#x)))","-ID:\\qt\\Tools\\QtCreator\\share\\qtcreator\\cplusplus\\wrappedMingwHeaders","-ID:\\qt\\Tools\\QtCreator\\share\\qtcreator\\cplusplus\\wrappedQtHeaders","-ID:\\qt\\Tools\\QtCreator\\share\\qtcreator\\cplusplus\\wrappedQtHeaders\\QtCore","-ID:\\qt\\code\\dpautoexam","-ID:\\qt\\code\\dpautoexam\\third_party\\pugixml","-ID:\\qt\\6.9.2\\mingw_64\\include","-ID:\\qt\\6.9.2\\mingw_64\\include\\QtWidgets","-ID:\\qt\\6.9.2\\mingw_64\\include\\QtGui","-ID:\\qt\\6.9.2\\mingw_64\\include\\QtCore","-ID:\\qt\\code\\dpautoexam\\build\\Desktop_Qt_6_9_2_MinGW_64_bit-Debug\\debug","-ID:\\qt\\code\\dpautoexam\\build\\Desktop_Qt_6_9_2_MinGW_64_bit-Debug","-ID:\\qt\\6.9.2\\mingw_64\\mkspecs\\win32-g++","-isystem","D:\\qt\\Tools\\mingw1310_64\\lib\\gcc\\x86_64-w64-mingw32\\13.1.0\\include\\c++","-isystem","D:\\qt\\Tools\\mingw1310_64\\lib\\gcc\\x86_64-w64-mingw32\\13.1.0\\include\\c++\\x86_64-w64-mingw32","-isystem","D:\\qt\\Tools\\mingw1310_64\\lib\\gcc\\x86_64-w64-mingw32\\13.1.0\\include\\c++\\backward","-isystem","D:\\qt\\Tools\\QtCreator\\bin\\clang\\lib\\clang\\20\\include","-isystem","D:\\qt\\Tools\\mingw1310_64\\x86_64-w64-mingw32\\include","-fmessage-length=0","-fdiagnostics-show-note-include-stack","-fretain-comments-from-system-headers","-fmacro-backtrace-limit=0","-ferror-limit=1000","-x","c++","D:\\qt\\code\\dpautoexam\\ChoiceQuestion.cpp"],"directory":"D:/qt/code/dpautoexam/build/Desktop_Qt_6_9_2_MinGW_64_bit-Debug/.qtc_clangd","file":"D:/qt/code/dpautoexam/ChoiceQuestion.cpp"},{"arguments":["clang","-Wno-documentation-unknown-command","-Wno-unknown-warning-option","-Wno-unknown-pragmas","-nostdinc","-nostdinc++","-g","-std=gnu++1z","-Wall","-Wextra","-Wextra","-fexceptions","-mthreads","-fsyntax-only","-m64","--target=x86_64-w64-mingw32","-DUNICODE","-D_UNICODE","-DWIN32","-DMINGW_HAS_SECURE_API","-DQT_QML_DEBUG","-DQT_WIDGETS_LIB","-DQT_GUI_LIB","-DQT_CORE_LIB","-DQT_NEEDS_QMAIN","-DQ_CREATOR_RUN","-DQT_ANNOTATE_FUNCTION(x)=__attribute__((annotate(#x)))","-ID:\\qt\\Tools\\QtCreator\\share\\qtcreator\\cplusplus\\wrappedMingwHeaders","-ID:\\qt\\Tools\\QtCreator\\share\\qtcreator\\cplusplus\\wrappedQtHeaders","-ID:\\qt\\Tools\\QtCreator\\share\\qtcreator\\cplusplus\\wrappedQtHeaders\\QtCore","-ID:\\qt\\code\\dpautoexam","-ID:\\qt\\code\\dpautoexam\\third_party\\pugixml","-ID:\\qt\\6.9.2\\mingw_64\\include","-ID:\\qt\\6.9.2\\mingw_64\\include\\QtWidgets","-ID:\\qt\\6.9.2\\mingw_64\\include\\QtGui","-ID:\\qt\\6.9.2\\mingw_64\\include\\QtCore","-ID:\\qt\\code\\dpautoexam\\build\\Desktop_Qt_6_9_2_MinGW_64_bit-Debug\\debug","-ID:\\qt\\code\\dpautoexam\\build\\Desktop_Qt_6_9_2_MinGW_64_bit-Debug","-ID:\\qt\\6.9.2\\mingw_64\\mkspecs\\win32-g++","-isystem","D:\\qt\\Tools\\mingw1310_64\\lib\\gcc\\x86_64-w64-mingw32\\13.1.0\\include\\c++","-isystem","D:\\qt\\Tools\\mingw1310_64\\lib\\gcc\\x86_64-w64-mingw32\\13.1.0\\include\\c++\\x86_64-w64-mingw32","-isystem","D:\\qt\\Tools\\mingw1310_64\\lib\\gcc\\x86_64-w64-mingw32\\13.1.0\\include\\c++\\backward","-isystem","D:\\qt\\Tools\\QtCreator\\bin\\clang\\lib\\clang\\20\\include","-isystem","D:\\qt\\Tools\\mingw1310_64\\x86_64-w64-mingw32\\include","-fmessage-length=0","-fdiagnostics-show-note-include-stack","-fretain-comments-from-system-headers","-fmacro-backtrace-limit=0","-ferror-limit=1000","-x","c++","D:\\qt\\code\\dpautoexam\\EssayDialog.cpp"],"directory":"D:/qt/code/dpautoexam/build/Desktop_Qt_6_9_2_MinGW_64_bit-Debug/.qtc_clangd","file":"D:/qt/code/dpautoexam/EssayDialog.cpp"},{"arguments":["clang","-Wno-documentation-unknown-command","-Wno-unknown-warning-option","-Wno-unknown-pragmas","-nostdinc","-nostdinc++","-g","-std=gnu++1z","-Wall","-Wextra","-Wextra","-fexceptions","-mthreads","-fsyntax-only","-m64","--target=x86_64-w64-mingw32","-DUNICODE","-D_UNICODE","-DWIN32","-DMINGW_HAS_SECURE_API","-DQT_QML_DEBUG","-DQT_WIDGETS_LIB","-DQT_GUI_LIB","-DQT_CORE_LIB","-DQT_NEEDS_QMAIN","-DQ_CREATOR_RUN","-DQT_ANNOTATE_FUNCTION(x)=__attribute__((annotate(#x)))","-ID:\\qt\\Tools\\QtCreator\\share\\qtcreator\\cplusplus\\wrappedMingwHeaders","-ID:\\qt\\Tools\\QtCreator\\share\\qtcreator\\cplusplus\\wrappedQtHeaders","-ID:\\qt\\Tools\\QtCreator\\share\\qtcreator\\cplusplus\\wrappedQtHeaders\\QtCore","-ID:\\qt\\code\\dpautoexam","-ID:\\qt\\code\\dpautoexam\\third_party\\pugixml","-ID:\\qt\\6.9.2\\mingw_64\\include","-ID:\\qt\\6.9.2\\mingw_64\\include\\QtWidgets","-ID:\\qt\\6.9.2\\mingw_64\\include\\QtGui","-ID:\\qt\\6.9.2\\mingw_64\\include\\QtCore","-ID:\\qt\\code\\dpautoexam\\build\\Desktop_Qt_6_9_2_MinGW_64_bit-Debug\\debug","-ID:\\qt\\code\\dpautoexam\\build\\Desktop_Qt_6_9_2_MinGW_64_bit-Debug","-ID:\\qt\\6.9.2\\mingw_64\\mkspecs\\win32-g++","-isystem","D:\\qt\\Tools\\mingw1310_64\\lib\\gcc\\x86_64-w64-mingw32\\13.1.0\\include\\c++","-isystem","D:\\qt\\Tools\\mingw1310_64\\lib\\gcc\\x86_64-w64-mingw32\\13.1.0\\include\\c++\\x86_64-w64-mingw32","-isystem","D:\\qt\\Tools\\mingw1310_64\\lib\\gcc\\x86_64-w64-mingw32\\13.1.0\\include\\c++\\backward","-isystem","D:\\qt\\Tools\\QtCreator\\bin\\clang\\lib\\clang\\20\\include","-isystem","D:\\qt\\Tools\\mingw1310_64\\x86_64-w64-mingw32\\include","-fmessage-length=0","-fdiagnostics-show-note-include-stack","-fretain-comments-from-system-headers","-fmacro-backtrace-limit=0","-ferror-limit=1000","-x","c++","D:\\qt\\code\\dpautoexam\\EssayQuestion.cpp"],"directory":"D:/qt/code/dpautoexam/build/Desktop_Qt_6_9_2_MinGW_64_bit-Debug/.qtc_clangd","file":"D:/qt/code/dpautoexam/EssayQuestion.cpp"},{"arguments":["clang","-Wno-documentation-unknown-command","-Wno-unknown-warning-option","-Wno-unknown-pragmas","-nostdinc","-nostdinc++","-g","-std=gnu++1z","-Wall","-Wextra","-Wextra","-fexceptions","-mthreads","-fsyntax-only","-m64","--target=x86_64-w64-mingw32","-DUNICODE","-D_UNICODE","-DWIN32","-DMINGW_HAS_SECURE_API","-DQT_QML_DEBUG","-DQT_WIDGETS_LIB","-DQT_GUI_LIB","-DQT_CORE_LIB","-DQT_NEEDS_QMAIN","-DQ_CREATOR_RUN","-DQT_ANNOTATE_FUNCTION(x)=__attribute__((annotate(#x)))","-ID:\\qt\\Tools\\QtCreator\\share\\qtcreator\\cplusplus\\wrappedMingwHeaders","-ID:\\qt\\Tools\\QtCreator\\share\\qtcreator\\cplusplus\\wrappedQtHeaders","-ID:\\qt\\Tools\\QtCreator\\share\\qtcreator\\cplusplus\\wrappedQtHeaders\\QtCore","-ID:\\qt\\code\\dpautoexam","-ID:\\qt\\code\\dpautoexam\\third_party\\pugixml","-ID:\\qt\\6.9.2\\mingw_64\\include","-ID:\\qt\\6.9.2\\mingw_64\\include\\QtWidgets","-ID:\\qt\\6.9.2\\mingw_64\\include\\QtGui","-ID:\\qt\\6.9.2\\mingw_64\\include\\QtCore","-ID:\\qt\\code\\dpautoexam\\build\\Desktop_Qt_6_9_2_MinGW_64_bit-Debug\\debug","-ID:\\qt\\code\\dpautoexam\\build\\Desktop_Qt_6_9_2_MinGW_64_bit-Debug","-ID:\\qt\\6.9.2\\mingw_64\\mkspecs\\win32-g++","-isystem","D:\\qt\\Tools\\mingw1310_64\\lib\\gcc\\x86_64-w64-mingw32\\13.1.0\\include\\c++","-isystem","D:\\qt\\Tools\\mingw1310_64\\lib\\gcc\\x86_64-w64-mingw32\\13.1.0\\include\\c++\\x86_64-w64-mingw32","-isystem","D:\\qt\\Tools\\mingw1310_64\\lib\\gcc\\x86_64-w64-mingw32\\13.1.0\\include\\c++\\backward","-isystem","D:\\qt\\Tools\\QtCreator\\bin\\clang\\lib\\clang\\20\\include","-isystem","D:\\qt\\Tools\\mingw1310_64\\x86_64-w64-mingw32\\include","-fmessage-length=0","-fdiagnostics-show-note-include-stack","-fretain-comments-from-system-headers","-fmacro-backtrace-limit=0","-ferror-limit=1000","-x","c++","D:\\qt\\code\\dpautoexam\\ExamDialog.cpp"],"directory":"D:/qt/code/dpautoexam/build/Desktop_Qt_6_9_2_MinGW_64_bit-Debug/.qtc_clangd","file":"D:/qt/code/dpautoexam/ExamDialog.cpp"},{"arguments":["clang","-Wno-documentation-unknown-command","-Wno-unknown-warning-option","-Wno-unknown-pragmas","-nostdinc","-nostdinc++","-g","-std=gnu++1z","-Wall","-Wextra","-Wextra","-fexceptions","-mthreads","-fsyntax-only","-m64","--target=x86_64-w64-mingw32","-DUNICODE","-D_UNICODE","-DWIN32","-DMINGW_HAS_SECURE_API","-DQT_QML_DEBUG","-DQT_WIDGETS_LIB","-DQT_GUI_LIB","-DQT_CORE_LIB","-DQT_NEEDS_QMAIN","-DQ_CREATOR_RUN","-DQT_ANNOTATE_FUNCTION(x)=__attribute__((annotate(#x)))","-ID:\\qt\\Tools\\QtCreator\\share\\qtcreator\\cplusplus\\wrappedMingwHeaders","-ID:\\qt\\Tools\\QtCreator\\share\\qtcreator\\cplusplus\\wrappedQtHeaders","-ID:\\qt\\Tools\\QtCreator\\share\\qtcreator\\cplusplus\\wrappedQtHeaders\\QtCore","-ID:\\qt\\code\\dpautoexam","-ID:\\qt\\code\\dpautoexam\\third_party\\pugixml","-ID:\\qt\\6.9.2\\mingw_64\\include","-ID:\\qt\\6.9.2\\mingw_64\\include\\QtWidgets","-ID:\\qt\\6.9.2\\mingw_64\\include\\QtGui","-ID:\\qt\\6.9.2\\mingw_64\\include\\QtCore","-ID:\\qt\\code\\dpautoexam\\build\\Desktop_Qt_6_9_2_MinGW_64_bit-Debug\\debug","-ID:\\qt\\code\\dpautoexam\\build\\Desktop_Qt_6_9_2_MinGW_64_bit-Debug","-ID:\\qt\\6.9.2\\mingw_64\\mkspecs\\win32-g++","-isystem","D:\\qt\\Tools\\mingw1310_64\\lib\\gcc\\x86_64-w64-mingw32\\13.1.0\\include\\c++","-isystem","D:\\qt\\Tools\\mingw1310_64\\lib\\gcc\\x86_64-w64-mingw32\\13.1.0\\include\\c++\\x86_64-w64-mingw32","-isystem","D:\\qt\\Tools\\mingw1310_64\\lib\\gcc\\x86_64-w64-mingw32\\13.1.0\\include\\c++\\backward","-isystem","D:\\qt\\Tools\\QtCreator\\bin\\clang\\lib\\clang\\20\\include","-isystem","D:\\qt\\Tools\\mingw1310_64\\x86_64-w64-mingw32\\include","-fmessage-length=0","-fdiagnostics-show-note-include-stack","-fretain-comments-from-system-headers","-fmacro-backtrace-limit=0","-ferror-limit=1000","-x","c++","D:\\qt\\code\\dpautoexam\\ExamSystem.cpp"],"directory":"D:/qt/code/dpautoexam/build/Desktop_Qt_6_9_2_MinGW_64_bit-Debug/.qtc_clangd","file":"D:/qt/code/dpautoexam/ExamSystem.cpp"},{"arguments":["clang","-Wno-documentation-unknown-command","-Wno-unknown-warning-option","-Wno-unknown-pragmas","-nostdinc","-nostdinc++","-g","-std=gnu++1z","-Wall","-Wextra","-Wextra","-fexceptions","-mthreads","-fsyntax-only","-m64","--target=x86_64-w64-mingw32","-DUNICODE","-D_UNICODE","-DWIN32","-DMINGW_HAS_SECURE_API","-DQT_QML_DEBUG","-DQT_WIDGETS_LIB","-DQT_GUI_LIB","-DQT_CORE_LIB","-DQT_NEEDS_QMAIN","-DQ_CREATOR_RUN","-DQT_ANNOTATE_FUNCTION(x)=__attribute__((annotate(#x)))","-ID:\\qt\\Tools\\QtCreator\\share\\qtcreator\\cplusplus\\wrappedMingwHeaders","-ID:\\qt\\Tools\\QtCreator\\share\\qtcreator\\cplusplus\\wrappedQtHeaders","-ID:\\qt\\Tools\\QtCreator\\share\\qtcreator\\cplusplus\\wrappedQtHeaders\\QtCore","-ID:\\qt\\code\\dpautoexam","-ID:\\qt\\code\\dpautoexam\\third_party\\pugixml","-ID:\\qt\\6.9.2\\mingw_64\\include","-ID:\\qt\\6.9.2\\mingw_64\\include\\QtWidgets","-ID:\\qt\\6.9.2\\mingw_64\\include\\QtGui","-ID:\\qt\\6.9.2\\mingw_64\\include\\QtCore","-ID:\\qt\\code\\dpautoexam\\build\\Desktop_Qt_6_9_2_MinGW_64_bit-Debug\\debug","-ID:\\qt\\code\\dpautoexam\\build\\Desktop_Qt_6_9_2_MinGW_64_bit-Debug","-ID:\\qt\\6.9.2\\mingw_64\\mkspecs\\win32-g++","-isystem","D:\\qt\\Tools\\mingw1310_64\\lib\\gcc\\x86_64-w64-mingw32\\13.1.0\\include\\c++","-isystem","D:\\qt\\Tools\\mingw1310_64\\lib\\gcc\\x86_64-w64-mingw32\\13.1.0\\include\\c++\\x86_64-w64-mingw32","-isystem","D:\\qt\\Tools\\mingw1310_64\\lib\\gcc\\x86_64-w64-mingw32\\13.1.0\\include\\c++\\backward","-isystem","D:\\qt\\Tools\\QtCreator\\bin\\clang\\lib\\clang\\20\\include","-isystem","D:\\qt\\Tools\\mingw1310_64\\x86_64-w64-mingw32\\include","-fmessage-length=0","-fdiagnostics-show-note-include-stack","-fretain-comments-from-system-headers","-fmacro-backtrace-limit=0","-ferror-limit=1000","-x","c++","D:\\qt\\code\\dpautoexam\\JudgementDialog.cpp"],"directory":"D:/qt/code/dpautoexam/build/Desktop_Qt_6_9_2_MinGW_64_bit-Debug/.qtc_clangd","file":"D:/qt/code/dpautoexam/JudgementDialog.cpp"},{"arguments":["clang","-Wno-documentation-unknown-command","-Wno-unknown-warning-option","-Wno-unknown-pragmas","-nostdinc","-nostdinc++","-g","-std=gnu++1z","-Wall","-Wextra","-Wextra","-fexceptions","-mthreads","-fsyntax-only","-m64","--target=x86_64-w64-mingw32","-DUNICODE","-D_UNICODE","-DWIN32","-DMINGW_HAS_SECURE_API","-DQT_QML_DEBUG","-DQT_WIDGETS_LIB","-DQT_GUI_LIB","-DQT_CORE_LIB","-DQT_NEEDS_QMAIN","-DQ_CREATOR_RUN","-DQT_ANNOTATE_FUNCTION(x)=__attribute__((annotate(#x)))","-ID:\\qt\\Tools\\QtCreator\\share\\qtcreator\\cplusplus\\wrappedMingwHeaders","-ID:\\qt\\Tools\\QtCreator\\share\\qtcreator\\cplusplus\\wrappedQtHeaders","-ID:\\qt\\Tools\\QtCreator\\share\\qtcreator\\cplusplus\\wrappedQtHeaders\\QtCore","-ID:\\qt\\code\\dpautoexam","-ID:\\qt\\code\\dpautoexam\\third_party\\pugixml","-ID:\\qt\\6.9.2\\mingw_64\\include","-ID:\\qt\\6.9.2\\mingw_64\\include\\QtWidgets","-ID:\\qt\\6.9.2\\mingw_64\\include\\QtGui","-ID:\\qt\\6.9.2\\mingw_64\\include\\QtCore","-ID:\\qt\\code\\dpautoexam\\build\\Desktop_Qt_6_9_2_MinGW_64_bit-Debug\\debug","-ID:\\qt\\code\\dpautoexam\\build\\Desktop_Qt_6_9_2_MinGW_64_bit-Debug","-ID:\\qt\\6.9.2\\mingw_64\\mkspecs\\win32-g++","-isystem","D:\\qt\\Tools\\mingw1310_64\\lib\\gcc\\x86_64-w64-mingw32\\13.1.0\\include\\c++","-isystem","D:\\qt\\Tools\\mingw1310_64\\lib\\gcc\\x86_64-w64-mingw32\\13.1.0\\include\\c++\\x86_64-w64-mingw32","-isystem","D:\\qt\\Tools\\mingw1310_64\\lib\\gcc\\x86_64-w64-mingw32\\13.1.0\\include\\c++\\backward","-isystem","D:\\qt\\Tools\\QtCreator\\bin\\clang\\lib\\clang\\20\\include","-isystem","D:\\qt\\Tools\\mingw1310_64\\x86_64-w64-mingw32\\include","-fmessage-length=0","-fdiagnostics-show-note-include-stack","-fretain-comments-from-system-headers","-fmacro-backtrace-limit=0","-ferror-limit=1000","-x","c++","D:\\qt\\code\\dpautoexam\\JudgementQuestion.cpp"],"directory":"D:/qt/code/dpautoexam/build/Desktop_Qt_6_9_2_MinGW_64_bit-Debug/.qtc_clangd","file":"D:/qt/code/dpautoexam/JudgementQuestion.cpp"},{"arguments":["clang","-Wno-documentation-unknown-command","-Wno-unknown-warning-option","-Wno-unknown-pragmas","-nostdinc","-nostdinc++","-g","-std=gnu++1z","-Wall","-Wextra","-Wextra","-fexceptions","-mthreads","-fsyntax-only","-m64","--target=x86_64-w64-mingw32","-DUNICODE","-D_UNICODE","-DWIN32","-DMINGW_HAS_SECURE_API","-DQT_QML_DEBUG","-DQT_WIDGETS_LIB","-DQT_GUI_LIB","-DQT_CORE_LIB","-DQT_NEEDS_QMAIN","-DQ_CREATOR_RUN","-DQT_ANNOTATE_FUNCTION(x)=__attribute__((annotate(#x)))","-ID:\\qt\\Tools\\QtCreator\\share\\qtcreator\\cplusplus\\wrappedMingwHeaders","-ID:\\qt\\Tools\\QtCreator\\share\\qtcreator\\cplusplus\\wrappedQtHeaders","-ID:\\qt\\Tools\\QtCreator\\share\\qtcreator\\cplusplus\\wrappedQtHeaders\\QtCore","-ID:\\qt\\code\\dpautoexam","-ID:\\qt\\code\\dpautoexam\\third_party\\pugixml","-ID:\\qt\\6.9.2\\mingw_64\\include","-ID:\\qt\\6.9.2\\mingw_64\\include\\QtWidgets","-ID:\\qt\\6.9.2\\mingw_64\\include\\QtGui","-ID:\\qt\\6.9.2\\mingw_64\\include\\QtCore","-ID:\\qt\\code\\dpautoexam\\build\\Desktop_Qt_6_9_2_MinGW_64_bit-Debug\\debug","-ID:\\qt\\code\\dpautoexam\\build\\Desktop_Qt_6_9_2_MinGW_64_bit-Debug","-ID:\\qt\\6.9.2\\mingw_64\\mkspecs\\win32-g++","-isystem","D:\\qt\\Tools\\mingw1310_64\\lib\\gcc\\x86_64-w64-mingw32\\13.1.0\\include\\c++","-isystem","D:\\qt\\Tools\\mingw1310_64\\lib\\gcc\\x86_64-w64-mingw32\\13.1.0\\include\\c++\\x86_64-w64-mingw32","-isystem","D:\\qt\\Tools\\mingw1310_64\\lib\\gcc\\x86_64-w64-mingw32\\13.1.0\\include\\c++\\backward","-isystem","D:\\qt\\Tools\\QtCreator\\bin\\clang\\lib\\clang\\20\\include","-isystem","D:\\qt\\Tools\\mingw1310_64\\x86_64-w64-mingw32\\include","-fmessage-length=0","-fdiagnostics-show-note-include-stack","-fretain-comments-from-system-headers","-fmacro-backtrace-limit=0","-ferror-limit=1000","-x","c++","D:\\qt\\code\\dpautoexam\\MultiplechoiceDialog.cpp"],"directory":"D:/qt/code/dpautoexam/build/Desktop_Qt_6_9_2_MinGW_64_bit-Debug/.qtc_clangd","file":"D:/qt/code/dpautoexam/MultiplechoiceDialog.cpp"},{"arguments":["clang","-Wno-documentation-unknown-command","-Wno-unknown-warning-option","-Wno-unknown-pragmas","-nostdinc","-nostdinc++","-g","-std=gnu++1z","-Wall","-Wextra","-Wextra","-fexceptions","-mthreads","-fsyntax-only","-m64","--target=x86_64-w64-mingw32","-DUNICODE","-D_UNICODE","-DWIN32","-DMINGW_HAS_SECURE_API","-DQT_QML_DEBUG","-DQT_WIDGETS_LIB","-DQT_GUI_LIB","-DQT_CORE_LIB","-DQT_NEEDS_QMAIN","-DQ_CREATOR_RUN","-DQT_ANNOTATE_FUNCTION(x)=__attribute__((annotate(#x)))","-ID:\\qt\\Tools\\QtCreator\\share\\qtcreator\\cplusplus\\wrappedMingwHeaders","-ID:\\qt\\Tools\\QtCreator\\share\\qtcreator\\cplusplus\\wrappedQtHeaders","-ID:\\qt\\Tools\\QtCreator\\share\\qtcreator\\cplusplus\\wrappedQtHeaders\\QtCore","-ID:\\qt\\code\\dpautoexam","-ID:\\qt\\code\\dpautoexam\\third_party\\pugixml","-ID:\\qt\\6.9.2\\mingw_64\\include","-ID:\\qt\\6.9.2\\mingw_64\\include\\QtWidgets","-ID:\\qt\\6.9.2\\mingw_64\\include\\QtGui","-ID:\\qt\\6.9.2\\mingw_64\\include\\QtCore","-ID:\\qt\\code\\dpautoexam\\build\\Desktop_Qt_6_9_2_MinGW_64_bit-Debug\\debug","-ID:\\qt\\code\\dpautoexam\\build\\Desktop_Qt_6_9_2_MinGW_64_bit-Debug","-ID:\\qt\\6.9.2\\mingw_64\\mkspecs\\win32-g++","-isystem","D:\\qt\\Tools\\mingw1310_64\\lib\\gcc\\x86_64-w64-mingw32\\13.1.0\\include\\c++","-isystem","D:\\qt\\Tools\\mingw1310_64\\lib\\gcc\\x86_64-w64-mingw32\\13.1.0\\include\\c++\\x86_64-w64-mingw32","-isystem","D:\\qt\\Tools\\mingw1310_64\\lib\\gcc\\x86_64-w64-mingw32\\13.1.0\\include\\c++\\backward","-isystem","D:\\qt\\Tools\\QtCreator\\bin\\clang\\lib\\clang\\20\\include","-isystem","D:\\qt\\Tools\\mingw1310_64\\x86_64-w64-mingw32\\include","-fmessage-length=0","-fdiagnostics-show-note-include-stack","-fretain-comments-from-system-headers","-fmacro-backtrace-limit=0","-ferror-limit=1000","-x","c++","D:\\qt\\code\\dpautoexam\\MutipleChoiceQuestion.cpp"],"directory":"D:/qt/code/dpautoexam/build/Desktop_Qt_6_9_2_MinGW_64_bit-Debug/.qtc_clangd","file":"D:/qt/code/dpautoexam/MutipleChoiceQuestion.cpp"},{"arguments":["clang","-Wno-documentation-unknown-command","-Wno-unknown-warning-option","-Wno-unknown-pragmas","-nostdinc","-nostdinc++","-g","-std=gnu++1z","-Wall","-Wextra","-Wextra","-fexceptions","-mthreads","-fsyntax-only","-m64","--target=x86_64-w64-mingw32","-DUNICODE","-D_UNICODE","-DWIN32","-DMINGW_HAS_SECURE_API","-DQT_QML_DEBUG","-DQT_WIDGETS_LIB","-DQT_GUI_LIB","-DQT_CORE_LIB","-DQT_NEEDS_QMAIN","-DQ_CREATOR_RUN","-DQT_ANNOTATE_FUNCTION(x)=__attribute__((annotate(#x)))","-ID:\\qt\\Tools\\QtCreator\\share\\qtcreator\\cplusplus\\wrappedMingwHeaders","-ID:\\qt\\Tools\\QtCreator\\share\\qtcreator\\cplusplus\\wrappedQtHeaders","-ID:\\qt\\Tools\\QtCreator\\share\\qtcreator\\cplusplus\\wrappedQtHeaders\\QtCore","-ID:\\qt\\code\\dpautoexam","-ID:\\qt\\code\\dpautoexam\\third_party\\pugixml","-ID:\\qt\\6.9.2\\mingw_64\\include","-ID:\\qt\\6.9.2\\mingw_64\\include\\QtWidgets","-ID:\\qt\\6.9.2\\mingw_64\\include\\QtGui","-ID:\\qt\\6.9.2\\mingw_64\\include\\QtCore","-ID:\\qt\\code\\dpautoexam\\build\\Desktop_Qt_6_9_2_MinGW_64_bit-Debug\\debug","-ID:\\qt\\code\\dpautoexam\\build\\Desktop_Qt_6_9_2_MinGW_64_bit-Debug","-ID:\\qt\\6.9.2\\mingw_64\\mkspecs\\win32-g++","-isystem","D:\\qt\\Tools\\mingw1310_64\\lib\\gcc\\x86_64-w64-mingw32\\13.1.0\\include\\c++","-isystem","D:\\qt\\Tools\\mingw1310_64\\lib\\gcc\\x86_64-w64-mingw32\\13.1.0\\include\\c++\\x86_64-w64-mingw32","-isystem","D:\\qt\\Tools\\mingw1310_64\\lib\\gcc\\x86_64-w64-mingw32\\13.1.0\\include\\c++\\backward","-isystem","D:\\qt\\Tools\\QtCreator\\bin\\clang\\lib\\clang\\20\\include","-isystem","D:\\qt\\Tools\\mingw1310_64\\x86_64-w64-mingw32\\include","-fmessage-length=0","-fdiagnostics-show-note-include-stack","-fretain-comments-from-system-headers","-fmacro-backtrace-limit=0","-ferror-limit=1000","-x","c++","D:\\qt\\code\\dpautoexam\\Paper.cpp"],"directory":"D:/qt/code/dpautoexam/build/Desktop_Qt_6_9_2_MinGW_64_bit-Debug/.qtc_clangd","file":"D:/qt/code/dpautoexam/Paper.cpp"},{"arguments":["clang","-Wno-documentation-unknown-command","-Wno-unknown-warning-option","-Wno-unknown-pragmas","-nostdinc","-nostdinc++","-g","-std=gnu++1z","-Wall","-Wextra","-Wextra","-fexceptions","-mthreads","-fsyntax-only","-m64","--target=x86_64-w64-mingw32","-DUNICODE","-D_UNICODE","-DWIN32","-DMINGW_HAS_SECURE_API","-DQT_QML_DEBUG","-DQT_WIDGETS_LIB","-DQT_GUI_LIB","-DQT_CORE_LIB","-DQT_NEEDS_QMAIN","-DQ_CREATOR_RUN","-DQT_ANNOTATE_FUNCTION(x)=__attribute__((annotate(#x)))","-ID:\\qt\\Tools\\QtCreator\\share\\qtcreator\\cplusplus\\wrappedMingwHeaders","-ID:\\qt\\Tools\\QtCreator\\share\\qtcreator\\cplusplus\\wrappedQtHeaders","-ID:\\qt\\Tools\\QtCreator\\share\\qtcreator\\cplusplus\\wrappedQtHeaders\\QtCore","-ID:\\qt\\code\\dpautoexam","-ID:\\qt\\code\\dpautoexam\\third_party\\pugixml","-ID:\\qt\\6.9.2\\mingw_64\\include","-ID:\\qt\\6.9.2\\mingw_64\\include\\QtWidgets","-ID:\\qt\\6.9.2\\mingw_64\\include\\QtGui","-ID:\\qt\\6.9.2\\mingw_64\\include\\QtCore","-ID:\\qt\\code\\dpautoexam\\build\\Desktop_Qt_6_9_2_MinGW_64_bit-Debug\\debug","-ID:\\qt\\code\\dpautoexam\\build\\Desktop_Qt_6_9_2_MinGW_64_bit-Debug","-ID:\\qt\\6.9.2\\mingw_64\\mkspecs\\win32-g++","-isystem","D:\\qt\\Tools\\mingw1310_64\\lib\\gcc\\x86_64-w64-mingw32\\13.1.0\\include\\c++","-isystem","D:\\qt\\Tools\\mingw1310_64\\lib\\gcc\\x86_64-w64-mingw32\\13.1.0\\include\\c++\\x86_64-w64-mingw32","-isystem","D:\\qt\\Tools\\mingw1310_64\\lib\\gcc\\x86_64-w64-mingw32\\13.1.0\\include\\c++\\backward","-isystem","D:\\qt\\Tools\\QtCreator\\bin\\clang\\lib\\clang\\20\\include","-isystem","D:\\qt\\Tools\\mingw1310_64\\x86_64-w64-mingw32\\include","-fmessage-length=0","-fdiagnostics-show-note-include-stack","-fretain-comments-from-system-headers","-fmacro-backtrace-limit=0","-ferror-limit=1000","-x","c++","D:\\qt\\code\\dpautoexam\\Question.cpp"],"directory":"D:/qt/code/dpautoexam/build/Desktop_Qt_6_9_2_MinGW_64_bit-Debug/.qtc_clangd","file":"D:/qt/code/dpautoexam/Question.cpp"},{"arguments":["clang","-Wno-documentation-unknown-command","-Wno-unknown-warning-option","-Wno-unknown-pragmas","-nostdinc","-nostdinc++","-g","-std=gnu++1z","-Wall","-Wextra","-Wextra","-fexceptions","-mthreads","-fsyntax-only","-m64","--target=x86_64-w64-mingw32","-DUNICODE","-D_UNICODE","-DWIN32","-DMINGW_HAS_SECURE_API","-DQT_QML_DEBUG","-DQT_WIDGETS_LIB","-DQT_GUI_LIB","-DQT_CORE_LIB","-DQT_NEEDS_QMAIN","-DQ_CREATOR_RUN","-DQT_ANNOTATE_FUNCTION(x)=__attribute__((annotate(#x)))","-ID:\\qt\\Tools\\QtCreator\\share\\qtcreator\\cplusplus\\wrappedMingwHeaders","-ID:\\qt\\Tools\\QtCreator\\share\\qtcreator\\cplusplus\\wrappedQtHeaders","-ID:\\qt\\Tools\\QtCreator\\share\\qtcreator\\cplusplus\\wrappedQtHeaders\\QtCore","-ID:\\qt\\code\\dpautoexam","-ID:\\qt\\code\\dpautoexam\\third_party\\pugixml","-ID:\\qt\\6.9.2\\mingw_64\\include","-ID:\\qt\\6.9.2\\mingw_64\\include\\QtWidgets","-ID:\\qt\\6.9.2\\mingw_64\\include\\QtGui","-ID:\\qt\\6.9.2\\mingw_64\\include\\QtCore","-ID:\\qt\\code\\dpautoexam\\build\\Desktop_Qt_6_9_2_MinGW_64_bit-Debug\\debug","-ID:\\qt\\code\\dpautoexam\\build\\Desktop_Qt_6_9_2_MinGW_64_bit-Debug","-ID:\\qt\\6.9.2\\mingw_64\\mkspecs\\win32-g++","-isystem","D:\\qt\\Tools\\mingw1310_64\\lib\\gcc\\x86_64-w64-mingw32\\13.1.0\\include\\c++","-isystem","D:\\qt\\Tools\\mingw1310_64\\lib\\gcc\\x86_64-w64-mingw32\\13.1.0\\include\\c++\\x86_64-w64-mingw32","-isystem","D:\\qt\\Tools\\mingw1310_64\\lib\\gcc\\x86_64-w64-mingw32\\13.1.0\\include\\c++\\backward","-isystem","D:\\qt\\Tools\\QtCreator\\bin\\clang\\lib\\clang\\20\\include","-isystem","D:\\qt\\Tools\\mingw1310_64\\x86_64-w64-mingw32\\include","-fmessage-length=0","-fdiagnostics-show-note-include-stack","-fretain-comments-from-system-headers","-fmacro-backtrace-limit=0","-ferror-limit=1000","-x","c++","D:\\qt\\code\\dpautoexam\\SingleChoiceDialog.cpp"],"directory":"D:/qt/code/dpautoexam/build/Desktop_Qt_6_9_2_MinGW_64_bit-Debug/.qtc_clangd","file":"D:/qt/code/dpautoexam/SingleChoiceDialog.cpp"},{"arguments":["clang","-Wno-documentation-unknown-command","-Wno-unknown-warning-option","-Wno-unknown-pragmas","-nostdinc","-nostdinc++","-g","-std=gnu++1z","-Wall","-Wextra","-Wextra","-fexceptions","-mthreads","-fsyntax-only","-m64","--target=x86_64-w64-mingw32","-DUNICODE","-D_UNICODE","-DWIN32","-DMINGW_HAS_SECURE_API","-DQT_QML_DEBUG","-DQT_WIDGETS_LIB","-DQT_GUI_LIB","-DQT_CORE_LIB","-DQT_NEEDS_QMAIN","-DQ_CREATOR_RUN","-DQT_ANNOTATE_FUNCTION(x)=__attribute__((annotate(#x)))","-ID:\\qt\\Tools\\QtCreator\\share\\qtcreator\\cplusplus\\wrappedMingwHeaders","-ID:\\qt\\Tools\\QtCreator\\share\\qtcreator\\cplusplus\\wrappedQtHeaders","-ID:\\qt\\Tools\\QtCreator\\share\\qtcreator\\cplusplus\\wrappedQtHeaders\\QtCore","-ID:\\qt\\code\\dpautoexam","-ID:\\qt\\code\\dpautoexam\\third_party\\pugixml","-ID:\\qt\\6.9.2\\mingw_64\\include","-ID:\\qt\\6.9.2\\mingw_64\\include\\QtWidgets","-ID:\\qt\\6.9.2\\mingw_64\\include\\QtGui","-ID:\\qt\\6.9.2\\mingw_64\\include\\QtCore","-ID:\\qt\\code\\dpautoexam\\build\\Desktop_Qt_6_9_2_MinGW_64_bit-Debug\\debug","-ID:\\qt\\code\\dpautoexam\\build\\Desktop_Qt_6_9_2_MinGW_64_bit-Debug","-ID:\\qt\\6.9.2\\mingw_64\\mkspecs\\win32-g++","-isystem","D:\\qt\\Tools\\mingw1310_64\\lib\\gcc\\x86_64-w64-mingw32\\13.1.0\\include\\c++","-isystem","D:\\qt\\Tools\\mingw1310_64\\lib\\gcc\\x86_64-w64-mingw32\\13.1.0\\include\\c++\\x86_64-w64-mingw32","-isystem","D:\\qt\\Tools\\mingw1310_64\\lib\\gcc\\x86_64-w64-mingw32\\13.1.0\\include\\c++\\backward","-isystem","D:\\qt\\Tools\\QtCreator\\bin\\clang\\lib\\clang\\20\\include","-isystem","D:\\qt\\Tools\\mingw1310_64\\x86_64-w64-mingw32\\include","-fmessage-length=0","-fdiagnostics-show-note-include-stack","-fretain-comments-from-system-headers","-fmacro-backtrace-limit=0","-ferror-limit=1000","-x","c++","D:\\qt\\code\\dpautoexam\\SingleChoiceQuestion.cpp"],"directory":"D:/qt/code/dpautoexam/build/Desktop_Qt_6_9_2_MinGW_64_bit-Debug/.qtc_clangd","file":"D:/qt/code/dpautoexam/SingleChoiceQuestion.cpp"},{"arguments":["clang","-Wno-documentation-unknown-command","-Wno-unknown-warning-option","-Wno-unknown-pragmas","-nostdinc","-nostdinc++","-g","-std=gnu++1z","-Wall","-Wextra","-Wextra","-fexceptions","-mthreads","-fsyntax-only","-m64","--target=x86_64-w64-mingw32","-DUNICODE","-D_UNICODE","-DWIN32","-DMINGW_HAS_SECURE_API","-DQT_QML_DEBUG","-DQT_WIDGETS_LIB","-DQT_GUI_LIB","-DQT_CORE_LIB","-DQT_NEEDS_QMAIN","-DQ_CREATOR_RUN","-DQT_ANNOTATE_FUNCTION(x)=__attribute__((annotate(#x)))","-ID:\\qt\\Tools\\QtCreator\\share\\qtcreator\\cplusplus\\wrappedMingwHeaders","-ID:\\qt\\Tools\\QtCreator\\share\\qtcreator\\cplusplus\\wrappedQtHeaders","-ID:\\qt\\Tools\\QtCreator\\share\\qtcreator\\cplusplus\\wrappedQtHeaders\\QtCore","-ID:\\qt\\code\\dpautoexam","-ID:\\qt\\code\\dpautoexam\\third_party\\pugixml","-ID:\\qt\\6.9.2\\mingw_64\\include","-ID:\\qt\\6.9.2\\mingw_64\\include\\QtWidgets","-ID:\\qt\\6.9.2\\mingw_64\\include\\QtGui","-ID:\\qt\\6.9.2\\mingw_64\\include\\QtCore","-ID:\\qt\\code\\dpautoexam\\build\\Desktop_Qt_6_9_2_MinGW_64_bit-Debug\\debug","-ID:\\qt\\code\\dpautoexam\\build\\Desktop_Qt_6_9_2_MinGW_64_bit-Debug","-ID:\\qt\\6.9.2\\mingw_64\\mkspecs\\win32-g++","-isystem","D:\\qt\\Tools\\mingw1310_64\\lib\\gcc\\x86_64-w64-mingw32\\13.1.0\\include\\c++","-isystem","D:\\qt\\Tools\\mingw1310_64\\lib\\gcc\\x86_64-w64-mingw32\\13.1.0\\include\\c++\\x86_64-w64-mingw32","-isystem","D:\\qt\\Tools\\mingw1310_64\\lib\\gcc\\x86_64-w64-mingw32\\13.1.0\\include\\c++\\backward","-isystem","D:\\qt\\Tools\\QtCreator\\bin\\clang\\lib\\clang\\20\\include","-isystem","D:\\qt\\Tools\\mingw1310_64\\x86_64-w64-mingw32\\include","-fmessage-length=0","-fdiagnostics-show-note-include-stack","-fretain-comments-from-system-headers","-fmacro-backtrace-limit=0","-ferror-limit=1000","-x","c++","D:\\qt\\code\\dpautoexam\\XMLHandler.cpp"],"directory":"D:/qt/code/dpautoexam/build/Desktop_Qt_6_9_2_MinGW_64_bit-Debug/.qtc_clangd","file":"D:/qt/code/dpautoexam/XMLHandler.cpp"},{"arguments":["clang","-Wno-documentation-unknown-command","-Wno-unknown-warning-option","-Wno-unknown-pragmas","-nostdinc","-nostdinc++","-g","-std=gnu++1z","-Wall","-Wextra","-Wextra","-fexceptions","-mthreads","-fsyntax-only","-m64","--target=x86_64-w64-mingw32","-DUNICODE","-D_UNICODE","-DWIN32","-DMINGW_HAS_SECURE_API","-DQT_QML_DEBUG","-DQT_WIDGETS_LIB","-DQT_GUI_LIB","-DQT_CORE_LIB","-DQT_NEEDS_QMAIN","-DQ_CREATOR_RUN","-DQT_ANNOTATE_FUNCTION(x)=__attribute__((annotate(#x)))","-ID:\\qt\\Tools\\QtCreator\\share\\qtcreator\\cplusplus\\wrappedMingwHeaders","-ID:\\qt\\Tools\\QtCreator\\share\\qtcreator\\cplusplus\\wrappedQtHeaders","-ID:\\qt\\Tools\\QtCreator\\share\\qtcreator\\cplusplus\\wrappedQtHeaders\\QtCore","-ID:\\qt\\code\\dpautoexam","-ID:\\qt\\code\\dpautoexam\\third_party\\pugixml","-ID:\\qt\\6.9.2\\mingw_64\\include","-ID:\\qt\\6.9.2\\mingw_64\\include\\QtWidgets","-ID:\\qt\\6.9.2\\mingw_64\\include\\QtGui","-ID:\\qt\\6.9.2\\mingw_64\\include\\QtCore","-ID:\\qt\\code\\dpautoexam\\build\\Desktop_Qt_6_9_2_MinGW_64_bit-Debug\\debug","-ID:\\qt\\code\\dpautoexam\\build\\Desktop_Qt_6_9_2_MinGW_64_bit-Debug","-ID:\\qt\\6.9.2\\mingw_64\\mkspecs\\win32-g++","-isystem","D:\\qt\\Tools\\mingw1310_64\\lib\\gcc\\x86_64-w64-mingw32\\13.1.0\\include\\c++","-isystem","D:\\qt\\Tools\\mingw1310_64\\lib\\gcc\\x86_64-w64-mingw32\\13.1.0\\include\\c++\\x86_64-w64-mingw32","-isystem","D:\\qt\\Tools\\mingw1310_64\\lib\\gcc\\x86_64-w64-mingw32\\13.1.0\\include\\c++\\backward","-isystem","D:\\qt\\Tools\\QtCreator\\bin\\clang\\lib\\clang\\20\\include","-isystem","D:\\qt\\Tools\\mingw1310_64\\x86_64-w64-mingw32\\include","-fmessage-length=0","-fdiagnostics-show-note-include-stack","-fretain-comments-from-system-headers","-fmacro-backtrace-limit=0","-ferror-limit=1000","-x","c++","D:\\qt\\code\\dpautoexam\\main.cpp"],"directory":"D:/qt/code/dpautoexam/build/Desktop_Qt_6_9_2_MinGW_64_bit-Debug/.qtc_clangd","file":"D:/qt/code/dpautoexam/main.cpp"},{"arguments":["clang","-Wno-documentation-unknown-command","-Wno-unknown-warning-option","-Wno-unknown-pragmas","-nostdinc","-nostdinc++","-g","-std=gnu++1z","-Wall","-Wextra","-Wextra","-fexceptions","-mthreads","-fsyntax-only","-m64","--target=x86_64-w64-mingw32","-DUNICODE","-D_UNICODE","-DWIN32","-DMINGW_HAS_SECURE_API","-DQT_QML_DEBUG","-DQT_WIDGETS_LIB","-DQT_GUI_LIB","-DQT_CORE_LIB","-DQT_NEEDS_QMAIN","-DQ_CREATOR_RUN","-DQT_ANNOTATE_FUNCTION(x)=__attribute__((annotate(#x)))","-ID:\\qt\\Tools\\QtCreator\\share\\qtcreator\\cplusplus\\wrappedMingwHeaders","-ID:\\qt\\Tools\\QtCreator\\share\\qtcreator\\cplusplus\\wrappedQtHeaders","-ID:\\qt\\Tools\\QtCreator\\share\\qtcreator\\cplusplus\\wrappedQtHeaders\\QtCore","-ID:\\qt\\code\\dpautoexam","-ID:\\qt\\code\\dpautoexam\\third_party\\pugixml","-ID:\\qt\\6.9.2\\mingw_64\\include","-ID:\\qt\\6.9.2\\mingw_64\\include\\QtWidgets","-ID:\\qt\\6.9.2\\mingw_64\\include\\QtGui","-ID:\\qt\\6.9.2\\mingw_64\\include\\QtCore","-ID:\\qt\\code\\dpautoexam\\build\\Desktop_Qt_6_9_2_MinGW_64_bit-Debug\\debug","-ID:\\qt\\code\\dpautoexam\\build\\Desktop_Qt_6_9_2_MinGW_64_bit-Debug","-ID:\\qt\\6.9.2\\mingw_64\\mkspecs\\win32-g++","-isystem","D:\\qt\\Tools\\mingw1310_64\\lib\\gcc\\x86_64-w64-mingw32\\13.1.0\\include\\c++","-isystem","D:\\qt\\Tools\\mingw1310_64\\lib\\gcc\\x86_64-w64-mingw32\\13.1.0\\include\\c++\\x86_64-w64-mingw32","-isystem","D:\\qt\\Tools\\mingw1310_64\\lib\\gcc\\x86_64-w64-mingw32\\13.1.0\\include\\c++\\backward","-isystem","D:\\qt\\Tools\\QtCreator\\bin\\clang\\lib\\clang\\20\\include","-isystem","D:\\qt\\Tools\\mingw1310_64\\x86_64-w64-mingw32\\include","-fmessage-length=0","-fdiagnostics-show-note-include-stack","-fretain-comments-from-system-headers","-fmacro-backtrace-limit=0","-ferror-limit=1000","-x","c++","D:\\qt\\code\\dpautoexam\\mainwindow.cpp"],"directory":"D:/qt/code/dpautoexam/build/Desktop_Qt_6_9_2_MinGW_64_bit-Debug/.qtc_clangd","file":"D:/qt/code/dpautoexam/mainwindow.cpp"},{"arguments":["clang","-Wno-documentation-unknown-command","-Wno-unknown-warning-option","-Wno-unknown-pragmas","-nostdinc","-nostdinc++","-g","-std=gnu++1z","-Wall","-Wextra","-Wextra","-fexceptions","-mthreads","-fsyntax-only","-m64","--target=x86_64-w64-mingw32","-DUNICODE","-D_UNICODE","-DWIN32","-DMINGW_HAS_SECURE_API","-DQT_QML_DEBUG","-DQT_WIDGETS_LIB","-DQT_GUI_LIB","-DQT_CORE_LIB","-DQT_NEEDS_QMAIN","-DQ_CREATOR_RUN","-DQT_ANNOTATE_FUNCTION(x)=__attribute__((annotate(#x)))","-ID:\\qt\\Tools\\QtCreator\\share\\qtcreator\\cplusplus\\wrappedMingwHeaders","-ID:\\qt\\Tools\\QtCreator\\share\\qtcreator\\cplusplus\\wrappedQtHeaders","-ID:\\qt\\Tools\\QtCreator\\share\\qtcreator\\cplusplus\\wrappedQtHeaders\\QtCore","-ID:\\qt\\code\\dpautoexam","-ID:\\qt\\code\\dpautoexam\\third_party\\pugixml","-ID:\\qt\\6.9.2\\mingw_64\\include","-ID:\\qt\\6.9.2\\mingw_64\\include\\QtWidgets","-ID:\\qt\\6.9.2\\mingw_64\\include\\QtGui","-ID:\\qt\\6.9.2\\mingw_64\\include\\QtCore","-ID:\\qt\\code\\dpautoexam\\build\\Desktop_Qt_6_9_2_MinGW_64_bit-Debug\\debug","-ID:\\qt\\code\\dpautoexam\\build\\Desktop_Qt_6_9_2_MinGW_64_bit-Debug","-ID:\\qt\\6.9.2\\mingw_64\\mkspecs\\win32-g++","-isystem","D:\\qt\\Tools\\mingw1310_64\\lib\\gcc\\x86_64-w64-mingw32\\13.1.0\\include\\c++","-isystem","D:\\qt\\Tools\\mingw1310_64\\lib\\gcc\\x86_64-w64-mingw32\\13.1.0\\include\\c++\\x86_64-w64-mingw32","-isystem","D:\\qt\\Tools\\mingw1310_64\\lib\\gcc\\x86_64-w64-mingw32\\13.1.0\\include\\c++\\backward","-isystem","D:\\qt\\Tools\\QtCreator\\bin\\clang\\lib\\clang\\20\\include","-isystem","D:\\qt\\Tools\\mingw1310_64\\x86_64-w64-mingw32\\include","-fmessage-length=0","-fdiagnostics-show-note-include-stack","-fretain-comments-from-system-headers","-fmacro-backtrace-limit=0","-ferror-limit=1000","-x","c++","D:\\qt\\code\\dpautoexam\\third_party\\pugixml\\pugixml.cpp"],"directory":"D:/qt/code/dpautoexam/build/Desktop_Qt_6_9_2_MinGW_64_bit-Debug/.qtc_clangd","file":"D:/qt/code/dpautoexam/third_party/pugixml/pugixml.cpp"},{"arguments":["clang","-Wno-documentation-unknown-command","-Wno-unknown-warning-option","-Wno-unknown-pragmas","-nostdinc","-nostdinc++","-g","-std=gnu++1z","-Wall","-Wextra","-Wextra","-fexceptions","-mthreads","-fsyntax-only","-m64","--target=x86_64-w64-mingw32","-DUNICODE","-D_UNICODE","-DWIN32","-DMINGW_HAS_SECURE_API","-DQT_QML_DEBUG","-DQT_WIDGETS_LIB","-DQT_GUI_LIB","-DQT_CORE_LIB","-DQT_NEEDS_QMAIN","-DQ_CREATOR_RUN","-DQT_ANNOTATE_FUNCTION(x)=__attribute__((annotate(#x)))","-ID:\\qt\\Tools\\QtCreator\\share\\qtcreator\\cplusplus\\wrappedMingwHeaders","-ID:\\qt\\Tools\\QtCreator\\share\\qtcreator\\cplusplus\\wrappedQtHeaders","-ID:\\qt\\Tools\\QtCreator\\share\\qtcreator\\cplusplus\\wrappedQtHeaders\\QtCore","-ID:\\qt\\code\\dpautoexam","-ID:\\qt\\code\\dpautoexam\\third_party\\pugixml","-ID:\\qt\\6.9.2\\mingw_64\\include","-ID:\\qt\\6.9.2\\mingw_64\\include\\QtWidgets","-ID:\\qt\\6.9.2\\mingw_64\\include\\QtGui","-ID:\\qt\\6.9.2\\mingw_64\\include\\QtCore","-ID:\\qt\\code\\dpautoexam\\build\\Desktop_Qt_6_9_2_MinGW_64_bit-Debug\\debug","-ID:\\qt\\code\\dpautoexam\\build\\Desktop_Qt_6_9_2_MinGW_64_bit-Debug","-ID:\\qt\\6.9.2\\mingw_64\\mkspecs\\win32-g++","-isystem","D:\\qt\\Tools\\mingw1310_64\\lib\\gcc\\x86_64-w64-mingw32\\13.1.0\\include\\c++","-isystem","D:\\qt\\Tools\\mingw1310_64\\lib\\gcc\\x86_64-w64-mingw32\\13.1.0\\include\\c++\\x86_64-w64-mingw32","-isystem","D:\\qt\\Tools\\mingw1310_64\\lib\\gcc\\x86_64-w64-mingw32\\13.1.0\\include\\c++\\backward","-isystem","D:\\qt\\Tools\\QtCreator\\bin\\clang\\lib\\clang\\20\\include","-isystem","D:\\qt\\Tools\\mingw1310_64\\x86_64-w64-mingw32\\include","-fmessage-length=0","-fdiagnostics-show-note-include-stack","-fretain-comments-from-system-headers","-fmacro-backtrace-limit=0","-ferror-limit=1000","-x","c++-header","D:\\qt\\code\\dpautoexam\\ChoiceQuestion.h"],"directory":"D:/qt/code/dpautoexam/build/Desktop_Qt_6_9_2_MinGW_64_bit-Debug/.qtc_clangd","file":"D:/qt/code/dpautoexam/ChoiceQuestion.h"},{"arguments":["clang","-Wno-documentation-unknown-command","-Wno-unknown-warning-option","-Wno-unknown-pragmas","-nostdinc","-nostdinc++","-g","-std=gnu++1z","-Wall","-Wextra","-Wextra","-fexceptions","-mthreads","-fsyntax-only","-m64","--target=x86_64-w64-mingw32","-DUNICODE","-D_UNICODE","-DWIN32","-DMINGW_HAS_SECURE_API","-DQT_QML_DEBUG","-DQT_WIDGETS_LIB","-DQT_GUI_LIB","-DQT_CORE_LIB","-DQT_NEEDS_QMAIN","-DQ_CREATOR_RUN","-DQT_ANNOTATE_FUNCTION(x)=__attribute__((annotate(#x)))","-ID:\\qt\\Tools\\QtCreator\\share\\qtcreator\\cplusplus\\wrappedMingwHeaders","-ID:\\qt\\Tools\\QtCreator\\share\\qtcreator\\cplusplus\\wrappedQtHeaders","-ID:\\qt\\Tools\\QtCreator\\share\\qtcreator\\cplusplus\\wrappedQtHeaders\\QtCore","-ID:\\qt\\code\\dpautoexam","-ID:\\qt\\code\\dpautoexam\\third_party\\pugixml","-ID:\\qt\\6.9.2\\mingw_64\\include","-ID:\\qt\\6.9.2\\mingw_64\\include\\QtWidgets","-ID:\\qt\\6.9.2\\mingw_64\\include\\QtGui","-ID:\\qt\\6.9.2\\mingw_64\\include\\QtCore","-ID:\\qt\\code\\dpautoexam\\build\\Desktop_Qt_6_9_2_MinGW_64_bit-Debug\\debug","-ID:\\qt\\code\\dpautoexam\\build\\Desktop_Qt_6_9_2_MinGW_64_bit-Debug","-ID:\\qt\\6.9.2\\mingw_64\\mkspecs\\win32-g++","-isystem","D:\\qt\\Tools\\mingw1310_64\\lib\\gcc\\x86_64-w64-mingw32\\13.1.0\\include\\c++","-isystem","D:\\qt\\Tools\\mingw1310_64\\lib\\gcc\\x86_64-w64-mingw32\\13.1.0\\include\\c++\\x86_64-w64-mingw32","-isystem","D:\\qt\\Tools\\mingw1310_64\\lib\\gcc\\x86_64-w64-mingw32\\13.1.0\\include\\c++\\backward","-isystem","D:\\qt\\Tools\\QtCreator\\bin\\clang\\lib\\clang\\20\\include","-isystem","D:\\qt\\Tools\\mingw1310_64\\x86_64-w64-mingw32\\include","-fmessage-length=0","-fdiagnostics-show-note-include-stack","-fretain-comments-from-system-headers","-fmacro-backtrace-limit=0","-ferror-limit=1000","-x","c++-header","D:\\qt\\code\\dpautoexam\\EssayDialog.h"],"directory":"D:/qt/code/dpautoexam/build/Desktop_Qt_6_9_2_MinGW_64_bit-Debug/.qtc_clangd","file":"D:/qt/code/dpautoexam/EssayDialog.h"},{"arguments":["clang","-Wno-documentation-unknown-command","-Wno-unknown-warning-option","-Wno-unknown-pragmas","-nostdinc","-nostdinc++","-g","-std=gnu++1z","-Wall","-Wextra","-Wextra","-fexceptions","-mthreads","-fsyntax-only","-m64","--target=x86_64-w64-mingw32","-DUNICODE","-D_UNICODE","-DWIN32","-DMINGW_HAS_SECURE_API","-DQT_QML_DEBUG","-DQT_WIDGETS_LIB","-DQT_GUI_LIB","-DQT_CORE_LIB","-DQT_NEEDS_QMAIN","-DQ_CREATOR_RUN","-DQT_ANNOTATE_FUNCTION(x)=__attribute__((annotate(#x)))","-ID:\\qt\\Tools\\QtCreator\\share\\qtcreator\\cplusplus\\wrappedMingwHeaders","-ID:\\qt\\Tools\\QtCreator\\share\\qtcreator\\cplusplus\\wrappedQtHeaders","-ID:\\qt\\Tools\\QtCreator\\share\\qtcreator\\cplusplus\\wrappedQtHeaders\\QtCore","-ID:\\qt\\code\\dpautoexam","-ID:\\qt\\code\\dpautoexam\\third_party\\pugixml","-ID:\\qt\\6.9.2\\mingw_64\\include","-ID:\\qt\\6.9.2\\mingw_64\\include\\QtWidgets","-ID:\\qt\\6.9.2\\mingw_64\\include\\QtGui","-ID:\\qt\\6.9.2\\mingw_64\\include\\QtCore","-ID:\\qt\\code\\dpautoexam\\build\\Desktop_Qt_6_9_2_MinGW_64_bit-Debug\\debug","-ID:\\qt\\code\\dpautoexam\\build\\Desktop_Qt_6_9_2_MinGW_64_bit-Debug","-ID:\\qt\\6.9.2\\mingw_64\\mkspecs\\win32-g++","-isystem","D:\\qt\\Tools\\mingw1310_64\\lib\\gcc\\x86_64-w64-mingw32\\13.1.0\\include\\c++","-isystem","D:\\qt\\Tools\\mingw1310_64\\lib\\gcc\\x86_64-w64-mingw32\\13.1.0\\include\\c++\\x86_64-w64-mingw32","-isystem","D:\\qt\\Tools\\mingw1310_64\\lib\\gcc\\x86_64-w64-mingw32\\13.1.0\\include\\c++\\backward","-isystem","D:\\qt\\Tools\\QtCreator\\bin\\clang\\lib\\clang\\20\\include","-isystem","D:\\qt\\Tools\\mingw1310_64\\x86_64-w64-mingw32\\include","-fmessage-length=0","-fdiagnostics-show-note-include-stack","-fretain-comments-from-system-headers","-fmacro-backtrace-limit=0","-ferror-limit=1000","-x","c++-header","D:\\qt\\code\\dpautoexam\\EssayQuestion.h"],"directory":"D:/qt/code/dpautoexam/build/Desktop_Qt_6_9_2_MinGW_64_bit-Debug/.qtc_clangd","file":"D:/qt/code/dpautoexam/EssayQuestion.h"},{"arguments":["clang","-Wno-documentation-unknown-command","-Wno-unknown-warning-option","-Wno-unknown-pragmas","-nostdinc","-nostdinc++","-g","-std=gnu++1z","-Wall","-Wextra","-Wextra","-fexceptions","-mthreads","-fsyntax-only","-m64","--target=x86_64-w64-mingw32","-DUNICODE","-D_UNICODE","-DWIN32","-DMINGW_HAS_SECURE_API","-DQT_QML_DEBUG","-DQT_WIDGETS_LIB","-DQT_GUI_LIB","-DQT_CORE_LIB","-DQT_NEEDS_QMAIN","-DQ_CREATOR_RUN","-DQT_ANNOTATE_FUNCTION(x)=__attribute__((annotate(#x)))","-ID:\\qt\\Tools\\QtCreator\\share\\qtcreator\\cplusplus\\wrappedMingwHeaders","-ID:\\qt\\Tools\\QtCreator\\share\\qtcreator\\cplusplus\\wrappedQtHeaders","-ID:\\qt\\Tools\\QtCreator\\share\\qtcreator\\cplusplus\\wrappedQtHeaders\\QtCore","-ID:\\qt\\code\\dpautoexam","-ID:\\qt\\code\\dpautoexam\\third_party\\pugixml","-ID:\\qt\\6.9.2\\mingw_64\\include","-ID:\\qt\\6.9.2\\mingw_64\\include\\QtWidgets","-ID:\\qt\\6.9.2\\mingw_64\\include\\QtGui","-ID:\\qt\\6.9.2\\mingw_64\\include\\QtCore","-ID:\\qt\\code\\dpautoexam\\build\\Desktop_Qt_6_9_2_MinGW_64_bit-Debug\\debug","-ID:\\qt\\code\\dpautoexam\\build\\Desktop_Qt_6_9_2_MinGW_64_bit-Debug","-ID:\\qt\\6.9.2\\mingw_64\\mkspecs\\win32-g++","-isystem","D:\\qt\\Tools\\mingw1310_64\\lib\\gcc\\x86_64-w64-mingw32\\13.1.0\\include\\c++","-isystem","D:\\qt\\Tools\\mingw1310_64\\lib\\gcc\\x86_64-w64-mingw32\\13.1.0\\include\\c++\\x86_64-w64-mingw32","-isystem","D:\\qt\\Tools\\mingw1310_64\\lib\\gcc\\x86_64-w64-mingw32\\13.1.0\\include\\c++\\backward","-isystem","D:\\qt\\Tools\\QtCreator\\bin\\clang\\lib\\clang\\20\\include","-isystem","D:\\qt\\Tools\\mingw1310_64\\x86_64-w64-mingw32\\include","-fmessage-length=0","-fdiagnostics-show-note-include-stack","-fretain-comments-from-system-headers","-fmacro-backtrace-limit=0","-ferror-limit=1000","-x","c++-header","D:\\qt\\code\\dpautoexam\\ExamDialog.h"],"directory":"D:/qt/code/dpautoexam/build/Desktop_Qt_6_9_2_MinGW_64_bit-Debug/.qtc_clangd","file":"D:/qt/code/dpautoexam/ExamDialog.h"},{"arguments":["clang","-Wno-documentation-unknown-command","-Wno-unknown-warning-option","-Wno-unknown-pragmas","-nostdinc","-nostdinc++","-g","-std=gnu++1z","-Wall","-Wextra","-Wextra","-fexceptions","-mthreads","-fsyntax-only","-m64","--target=x86_64-w64-mingw32","-DUNICODE","-D_UNICODE","-DWIN32","-DMINGW_HAS_SECURE_API","-DQT_QML_DEBUG","-DQT_WIDGETS_LIB","-DQT_GUI_LIB","-DQT_CORE_LIB","-DQT_NEEDS_QMAIN","-DQ_CREATOR_RUN","-DQT_ANNOTATE_FUNCTION(x)=__attribute__((annotate(#x)))","-ID:\\qt\\Tools\\QtCreator\\share\\qtcreator\\cplusplus\\wrappedMingwHeaders","-ID:\\qt\\Tools\\QtCreator\\share\\qtcreator\\cplusplus\\wrappedQtHeaders","-ID:\\qt\\Tools\\QtCreator\\share\\qtcreator\\cplusplus\\wrappedQtHeaders\\QtCore","-ID:\\qt\\code\\dpautoexam","-ID:\\qt\\code\\dpautoexam\\third_party\\pugixml","-ID:\\qt\\6.9.2\\mingw_64\\include","-ID:\\qt\\6.9.2\\mingw_64\\include\\QtWidgets","-ID:\\qt\\6.9.2\\mingw_64\\include\\QtGui","-ID:\\qt\\6.9.2\\mingw_64\\include\\QtCore","-ID:\\qt\\code\\dpautoexam\\build\\Desktop_Qt_6_9_2_MinGW_64_bit-Debug\\debug","-ID:\\qt\\code\\dpautoexam\\build\\Desktop_Qt_6_9_2_MinGW_64_bit-Debug","-ID:\\qt\\6.9.2\\mingw_64\\mkspecs\\win32-g++","-isystem","D:\\qt\\Tools\\mingw1310_64\\lib\\gcc\\x86_64-w64-mingw32\\13.1.0\\include\\c++","-isystem","D:\\qt\\Tools\\mingw1310_64\\lib\\gcc\\x86_64-w64-mingw32\\13.1.0\\include\\c++\\x86_64-w64-mingw32","-isystem","D:\\qt\\Tools\\mingw1310_64\\lib\\gcc\\x86_64-w64-mingw32\\13.1.0\\include\\c++\\backward","-isystem","D:\\qt\\Tools\\QtCreator\\bin\\clang\\lib\\clang\\20\\include","-isystem","D:\\qt\\Tools\\mingw1310_64\\x86_64-w64-mingw32\\include","-fmessage-length=0","-fdiagnostics-show-note-include-stack","-fretain-comments-from-system-headers","-fmacro-backtrace-limit=0","-ferror-limit=1000","-x","c++-header","D:\\qt\\code\\dpautoexam\\ExamSystem.h"],"directory":"D:/qt/code/dpautoexam/build/Desktop_Qt_6_9_2_MinGW_64_bit-Debug/.qtc_clangd","file":"D:/qt/code/dpautoexam/ExamSystem.h"},{"arguments":["clang","-Wno-documentation-unknown-command","-Wno-unknown-warning-option","-Wno-unknown-pragmas","-nostdinc","-nostdinc++","-g","-std=gnu++1z","-Wall","-Wextra","-Wextra","-fexceptions","-mthreads","-fsyntax-only","-m64","--target=x86_64-w64-mingw32","-DUNICODE","-D_UNICODE","-DWIN32","-DMINGW_HAS_SECURE_API","-DQT_QML_DEBUG","-DQT_WIDGETS_LIB","-DQT_GUI_LIB","-DQT_CORE_LIB","-DQT_NEEDS_QMAIN","-DQ_CREATOR_RUN","-DQT_ANNOTATE_FUNCTION(x)=__attribute__((annotate(#x)))","-ID:\\qt\\Tools\\QtCreator\\share\\qtcreator\\cplusplus\\wrappedMingwHeaders","-ID:\\qt\\Tools\\QtCreator\\share\\qtcreator\\cplusplus\\wrappedQtHeaders","-ID:\\qt\\Tools\\QtCreator\\share\\qtcreator\\cplusplus\\wrappedQtHeaders\\QtCore","-ID:\\qt\\code\\dpautoexam","-ID:\\qt\\code\\dpautoexam\\third_party\\pugixml","-ID:\\qt\\6.9.2\\mingw_64\\include","-ID:\\qt\\6.9.2\\mingw_64\\include\\QtWidgets","-ID:\\qt\\6.9.2\\mingw_64\\include\\QtGui","-ID:\\qt\\6.9.2\\mingw_64\\include\\QtCore","-ID:\\qt\\code\\dpautoexam\\build\\Desktop_Qt_6_9_2_MinGW_64_bit-Debug\\debug","-ID:\\qt\\code\\dpautoexam\\build\\Desktop_Qt_6_9_2_MinGW_64_bit-Debug","-ID:\\qt\\6.9.2\\mingw_64\\mkspecs\\win32-g++","-isystem","D:\\qt\\Tools\\mingw1310_64\\lib\\gcc\\x86_64-w64-mingw32\\13.1.0\\include\\c++","-isystem","D:\\qt\\Tools\\mingw1310_64\\lib\\gcc\\x86_64-w64-mingw32\\13.1.0\\include\\c++\\x86_64-w64-mingw32","-isystem","D:\\qt\\Tools\\mingw1310_64\\lib\\gcc\\x86_64-w64-mingw32\\13.1.0\\include\\c++\\backward","-isystem","D:\\qt\\Tools\\QtCreator\\bin\\clang\\lib\\clang\\20\\include","-isystem","D:\\qt\\Tools\\mingw1310_64\\x86_64-w64-mingw32\\include","-fmessage-length=0","-fdiagnostics-show-note-include-stack","-fretain-comments-from-system-headers","-fmacro-backtrace-limit=0","-ferror-limit=1000","-x","c++-header","D:\\qt\\code\\dpautoexam\\JudgementDialog.h"],"directory":"D:/qt/code/dpautoexam/build/Desktop_Qt_6_9_2_MinGW_64_bit-Debug/.qtc_clangd","file":"D:/qt/code/dpautoexam/JudgementDialog.h"},{"arguments":["clang","-Wno-documentation-unknown-command","-Wno-unknown-warning-option","-Wno-unknown-pragmas","-nostdinc","-nostdinc++","-g","-std=gnu++1z","-Wall","-Wextra","-Wextra","-fexceptions","-mthreads","-fsyntax-only","-m64","--target=x86_64-w64-mingw32","-DUNICODE","-D_UNICODE","-DWIN32","-DMINGW_HAS_SECURE_API","-DQT_QML_DEBUG","-DQT_WIDGETS_LIB","-DQT_GUI_LIB","-DQT_CORE_LIB","-DQT_NEEDS_QMAIN","-DQ_CREATOR_RUN","-DQT_ANNOTATE_FUNCTION(x)=__attribute__((annotate(#x)))","-ID:\\qt\\Tools\\QtCreator\\share\\qtcreator\\cplusplus\\wrappedMingwHeaders","-ID:\\qt\\Tools\\QtCreator\\share\\qtcreator\\cplusplus\\wrappedQtHeaders","-ID:\\qt\\Tools\\QtCreator\\share\\qtcreator\\cplusplus\\wrappedQtHeaders\\QtCore","-ID:\\qt\\code\\dpautoexam","-ID:\\qt\\code\\dpautoexam\\third_party\\pugixml","-ID:\\qt\\6.9.2\\mingw_64\\include","-ID:\\qt\\6.9.2\\mingw_64\\include\\QtWidgets","-ID:\\qt\\6.9.2\\mingw_64\\include\\QtGui","-ID:\\qt\\6.9.2\\mingw_64\\include\\QtCore","-ID:\\qt\\code\\dpautoexam\\build\\Desktop_Qt_6_9_2_MinGW_64_bit-Debug\\debug","-ID:\\qt\\code\\dpautoexam\\build\\Desktop_Qt_6_9_2_MinGW_64_bit-Debug","-ID:\\qt\\6.9.2\\mingw_64\\mkspecs\\win32-g++","-isystem","D:\\qt\\Tools\\mingw1310_64\\lib\\gcc\\x86_64-w64-mingw32\\13.1.0\\include\\c++","-isystem","D:\\qt\\Tools\\mingw1310_64\\lib\\gcc\\x86_64-w64-mingw32\\13.1.0\\include\\c++\\x86_64-w64-mingw32","-isystem","D:\\qt\\Tools\\mingw1310_64\\lib\\gcc\\x86_64-w64-mingw32\\13.1.0\\include\\c++\\backward","-isystem","D:\\qt\\Tools\\QtCreator\\bin\\clang\\lib\\clang\\20\\include","-isystem","D:\\qt\\Tools\\mingw1310_64\\x86_64-w64-mingw32\\include","-fmessage-length=0","-fdiagnostics-show-note-include-stack","-fretain-comments-from-system-headers","-fmacro-backtrace-limit=0","-ferror-limit=1000","-x","c++-header","D:\\qt\\code\\dpautoexam\\JudgementQuestion.h"],"directory":"D:/qt/code/dpautoexam/build/Desktop_Qt_6_9_2_MinGW_64_bit-Debug/.qtc_clangd","file":"D:/qt/code/dpautoexam/JudgementQuestion.h"},{"arguments":["clang","-Wno-documentation-unknown-command","-Wno-unknown-warning-option","-Wno-unknown-pragmas","-nostdinc","-nostdinc++","-g","-std=gnu++1z","-Wall","-Wextra","-Wextra","-fexceptions","-mthreads","-fsyntax-only","-m64","--target=x86_64-w64-mingw32","-DUNICODE","-D_UNICODE","-DWIN32","-DMINGW_HAS_SECURE_API","-DQT_QML_DEBUG","-DQT_WIDGETS_LIB","-DQT_GUI_LIB","-DQT_CORE_LIB","-DQT_NEEDS_QMAIN","-DQ_CREATOR_RUN","-DQT_ANNOTATE_FUNCTION(x)=__attribute__((annotate(#x)))","-ID:\\qt\\Tools\\QtCreator\\share\\qtcreator\\cplusplus\\wrappedMingwHeaders","-ID:\\qt\\Tools\\QtCreator\\share\\qtcreator\\cplusplus\\wrappedQtHeaders","-ID:\\qt\\Tools\\QtCreator\\share\\qtcreator\\cplusplus\\wrappedQtHeaders\\QtCore","-ID:\\qt\\code\\dpautoexam","-ID:\\qt\\code\\dpautoexam\\third_party\\pugixml","-ID:\\qt\\6.9.2\\mingw_64\\include","-ID:\\qt\\6.9.2\\mingw_64\\include\\QtWidgets","-ID:\\qt\\6.9.2\\mingw_64\\include\\QtGui","-ID:\\qt\\6.9.2\\mingw_64\\include\\QtCore","-ID:\\qt\\code\\dpautoexam\\build\\Desktop_Qt_6_9_2_MinGW_64_bit-Debug\\debug","-ID:\\qt\\code\\dpautoexam\\build\\Desktop_Qt_6_9_2_MinGW_64_bit-Debug","-ID:\\qt\\6.9.2\\mingw_64\\mkspecs\\win32-g++","-isystem","D:\\qt\\Tools\\mingw1310_64\\lib\\gcc\\x86_64-w64-mingw32\\13.1.0\\include\\c++","-isystem","D:\\qt\\Tools\\mingw1310_64\\lib\\gcc\\x86_64-w64-mingw32\\13.1.0\\include\\c++\\x86_64-w64-mingw32","-isystem","D:\\qt\\Tools\\mingw1310_64\\lib\\gcc\\x86_64-w64-mingw32\\13.1.0\\include\\c++\\backward","-isystem","D:\\qt\\Tools\\QtCreator\\bin\\clang\\lib\\clang\\20\\include","-isystem","D:\\qt\\Tools\\mingw1310_64\\x86_64-w64-mingw32\\include","-fmessage-length=0","-fdiagnostics-show-note-include-stack","-fretain-comments-from-system-headers","-fmacro-backtrace-limit=0","-ferror-limit=1000","-x","c++-header","D:\\qt\\code\\dpautoexam\\MultipleChoiceDialog.h"],"directory":"D:/qt/code/dpautoexam/build/Desktop_Qt_6_9_2_MinGW_64_bit-Debug/.qtc_clangd","file":"D:/qt/code/dpautoexam/MultipleChoiceDialog.h"},{"arguments":["clang","-Wno-documentation-unknown-command","-Wno-unknown-warning-option","-Wno-unknown-pragmas","-nostdinc","-nostdinc++","-g","-std=gnu++1z","-Wall","-Wextra","-Wextra","-fexceptions","-mthreads","-fsyntax-only","-m64","--target=x86_64-w64-mingw32","-DUNICODE","-D_UNICODE","-DWIN32","-DMINGW_HAS_SECURE_API","-DQT_QML_DEBUG","-DQT_WIDGETS_LIB","-DQT_GUI_LIB","-DQT_CORE_LIB","-DQT_NEEDS_QMAIN","-DQ_CREATOR_RUN","-DQT_ANNOTATE_FUNCTION(x)=__attribute__((annotate(#x)))","-ID:\\qt\\Tools\\QtCreator\\share\\qtcreator\\cplusplus\\wrappedMingwHeaders","-ID:\\qt\\Tools\\QtCreator\\share\\qtcreator\\cplusplus\\wrappedQtHeaders","-ID:\\qt\\Tools\\QtCreator\\share\\qtcreator\\cplusplus\\wrappedQtHeaders\\QtCore","-ID:\\qt\\code\\dpautoexam","-ID:\\qt\\code\\dpautoexam\\third_party\\pugixml","-ID:\\qt\\6.9.2\\mingw_64\\include","-ID:\\qt\\6.9.2\\mingw_64\\include\\QtWidgets","-ID:\\qt\\6.9.2\\mingw_64\\include\\QtGui","-ID:\\qt\\6.9.2\\mingw_64\\include\\QtCore","-ID:\\qt\\code\\dpautoexam\\build\\Desktop_Qt_6_9_2_MinGW_64_bit-Debug\\debug","-ID:\\qt\\code\\dpautoexam\\build\\Desktop_Qt_6_9_2_MinGW_64_bit-Debug","-ID:\\qt\\6.9.2\\mingw_64\\mkspecs\\win32-g++","-isystem","D:\\qt\\Tools\\mingw1310_64\\lib\\gcc\\x86_64-w64-mingw32\\13.1.0\\include\\c++","-isystem","D:\\qt\\Tools\\mingw1310_64\\lib\\gcc\\x86_64-w64-mingw32\\13.1.0\\include\\c++\\x86_64-w64-mingw32","-isystem","D:\\qt\\Tools\\mingw1310_64\\lib\\gcc\\x86_64-w64-mingw32\\13.1.0\\include\\c++\\backward","-isystem","D:\\qt\\Tools\\QtCreator\\bin\\clang\\lib\\clang\\20\\include","-isystem","D:\\qt\\Tools\\mingw1310_64\\x86_64-w64-mingw32\\include","-fmessage-length=0","-fdiagnostics-show-note-include-stack","-fretain-comments-from-system-headers","-fmacro-backtrace-limit=0","-ferror-limit=1000","-x","c++-header","D:\\qt\\code\\dpautoexam\\MultipleChoiceQuestion.h"],"directory":"D:/qt/code/dpautoexam/build/Desktop_Qt_6_9_2_MinGW_64_bit-Debug/.qtc_clangd","file":"D:/qt/code/dpautoexam/MultipleChoiceQuestion.h"},{"arguments":["clang","-Wno-documentation-unknown-command","-Wno-unknown-warning-option","-Wno-unknown-pragmas","-nostdinc","-nostdinc++","-g","-std=gnu++1z","-Wall","-Wextra","-Wextra","-fexceptions","-mthreads","-fsyntax-only","-m64","--target=x86_64-w64-mingw32","-DUNICODE","-D_UNICODE","-DWIN32","-DMINGW_HAS_SECURE_API","-DQT_QML_DEBUG","-DQT_WIDGETS_LIB","-DQT_GUI_LIB","-DQT_CORE_LIB","-DQT_NEEDS_QMAIN","-DQ_CREATOR_RUN","-DQT_ANNOTATE_FUNCTION(x)=__attribute__((annotate(#x)))","-ID:\\qt\\Tools\\QtCreator\\share\\qtcreator\\cplusplus\\wrappedMingwHeaders","-ID:\\qt\\Tools\\QtCreator\\share\\qtcreator\\cplusplus\\wrappedQtHeaders","-ID:\\qt\\Tools\\QtCreator\\share\\qtcreator\\cplusplus\\wrappedQtHeaders\\QtCore","-ID:\\qt\\code\\dpautoexam","-ID:\\qt\\code\\dpautoexam\\third_party\\pugixml","-ID:\\qt\\6.9.2\\mingw_64\\include","-ID:\\qt\\6.9.2\\mingw_64\\include\\QtWidgets","-ID:\\qt\\6.9.2\\mingw_64\\include\\QtGui","-ID:\\qt\\6.9.2\\mingw_64\\include\\QtCore","-ID:\\qt\\code\\dpautoexam\\build\\Desktop_Qt_6_9_2_MinGW_64_bit-Debug\\debug","-ID:\\qt\\code\\dpautoexam\\build\\Desktop_Qt_6_9_2_MinGW_64_bit-Debug","-ID:\\qt\\6.9.2\\mingw_64\\mkspecs\\win32-g++","-isystem","D:\\qt\\Tools\\mingw1310_64\\lib\\gcc\\x86_64-w64-mingw32\\13.1.0\\include\\c++","-isystem","D:\\qt\\Tools\\mingw1310_64\\lib\\gcc\\x86_64-w64-mingw32\\13.1.0\\include\\c++\\x86_64-w64-mingw32","-isystem","D:\\qt\\Tools\\mingw1310_64\\lib\\gcc\\x86_64-w64-mingw32\\13.1.0\\include\\c++\\backward","-isystem","D:\\qt\\Tools\\QtCreator\\bin\\clang\\lib\\clang\\20\\include","-isystem","D:\\qt\\Tools\\mingw1310_64\\x86_64-w64-mingw32\\include","-fmessage-length=0","-fdiagnostics-show-note-include-stack","-fretain-comments-from-system-headers","-fmacro-backtrace-limit=0","-ferror-limit=1000","-x","c++-header","D:\\qt\\code\\dpautoexam\\Paper.h"],"directory":"D:/qt/code/dpautoexam/build/Desktop_Qt_6_9_2_MinGW_64_bit-Debug/.qtc_clangd","file":"D:/qt/code/dpautoexam/Paper.h"},{"arguments":["clang","-Wno-documentation-unknown-command","-Wno-unknown-warning-option","-Wno-unknown-pragmas","-nostdinc","-nostdinc++","-g","-std=gnu++1z","-Wall","-Wextra","-Wextra","-fexceptions","-mthreads","-fsyntax-only","-m64","--target=x86_64-w64-mingw32","-DUNICODE","-D_UNICODE","-DWIN32","-DMINGW_HAS_SECURE_API","-DQT_QML_DEBUG","-DQT_WIDGETS_LIB","-DQT_GUI_LIB","-DQT_CORE_LIB","-DQT_NEEDS_QMAIN","-DQ_CREATOR_RUN","-DQT_ANNOTATE_FUNCTION(x)=__attribute__((annotate(#x)))","-ID:\\qt\\Tools\\QtCreator\\share\\qtcreator\\cplusplus\\wrappedMingwHeaders","-ID:\\qt\\Tools\\QtCreator\\share\\qtcreator\\cplusplus\\wrappedQtHeaders","-ID:\\qt\\Tools\\QtCreator\\share\\qtcreator\\cplusplus\\wrappedQtHeaders\\QtCore","-ID:\\qt\\code\\dpautoexam","-ID:\\qt\\code\\dpautoexam\\third_party\\pugixml","-ID:\\qt\\6.9.2\\mingw_64\\include","-ID:\\qt\\6.9.2\\mingw_64\\include\\QtWidgets","-ID:\\qt\\6.9.2\\mingw_64\\include\\QtGui","-ID:\\qt\\6.9.2\\mingw_64\\include\\QtCore","-ID:\\qt\\code\\dpautoexam\\build\\Desktop_Qt_6_9_2_MinGW_64_bit-Debug\\debug","-ID:\\qt\\code\\dpautoexam\\build\\Desktop_Qt_6_9_2_MinGW_64_bit-Debug","-ID:\\qt\\6.9.2\\mingw_64\\mkspecs\\win32-g++","-isystem","D:\\qt\\Tools\\mingw1310_64\\lib\\gcc\\x86_64-w64-mingw32\\13.1.0\\include\\c++","-isystem","D:\\qt\\Tools\\mingw1310_64\\lib\\gcc\\x86_64-w64-mingw32\\13.1.0\\include\\c++\\x86_64-w64-mingw32","-isystem","D:\\qt\\Tools\\mingw1310_64\\lib\\gcc\\x86_64-w64-mingw32\\13.1.0\\include\\c++\\backward","-isystem","D:\\qt\\Tools\\QtCreator\\bin\\clang\\lib\\clang\\20\\include","-isystem","D:\\qt\\Tools\\mingw1310_64\\x86_64-w64-mingw32\\include","-fmessage-length=0","-fdiagnostics-show-note-include-stack","-fretain-comments-from-system-headers","-fmacro-backtrace-limit=0","-ferror-limit=1000","-x","c++-header","D:\\qt\\code\\dpautoexam\\Question.h"],"directory":"D:/qt/code/dpautoexam/build/Desktop_Qt_6_9_2_MinGW_64_bit-Debug/.qtc_clangd","file":"D:/qt/code/dpautoexam/Question.h"},{"arguments":["clang","-Wno-documentation-unknown-command","-Wno-unknown-warning-option","-Wno-unknown-pragmas","-nostdinc","-nostdinc++","-g","-std=gnu++1z","-Wall","-Wextra","-Wextra","-fexceptions","-mthreads","-fsyntax-only","-m64","--target=x86_64-w64-mingw32","-DUNICODE","-D_UNICODE","-DWIN32","-DMINGW_HAS_SECURE_API","-DQT_QML_DEBUG","-DQT_WIDGETS_LIB","-DQT_GUI_LIB","-DQT_CORE_LIB","-DQT_NEEDS_QMAIN","-DQ_CREATOR_RUN","-DQT_ANNOTATE_FUNCTION(x)=__attribute__((annotate(#x)))","-ID:\\qt\\Tools\\QtCreator\\share\\qtcreator\\cplusplus\\wrappedMingwHeaders","-ID:\\qt\\Tools\\QtCreator\\share\\qtcreator\\cplusplus\\wrappedQtHeaders","-ID:\\qt\\Tools\\QtCreator\\share\\qtcreator\\cplusplus\\wrappedQtHeaders\\QtCore","-ID:\\qt\\code\\dpautoexam","-ID:\\qt\\code\\dpautoexam\\third_party\\pugixml","-ID:\\qt\\6.9.2\\mingw_64\\include","-ID:\\qt\\6.9.2\\mingw_64\\include\\QtWidgets","-ID:\\qt\\6.9.2\\mingw_64\\include\\QtGui","-ID:\\qt\\6.9.2\\mingw_64\\include\\QtCore","-ID:\\qt\\code\\dpautoexam\\build\\Desktop_Qt_6_9_2_MinGW_64_bit-Debug\\debug","-ID:\\qt\\code\\dpautoexam\\build\\Desktop_Qt_6_9_2_MinGW_64_bit-Debug","-ID:\\qt\\6.9.2\\mingw_64\\mkspecs\\win32-g++","-isystem","D:\\qt\\Tools\\mingw1310_64\\lib\\gcc\\x86_64-w64-mingw32\\13.1.0\\include\\c++","-isystem","D:\\qt\\Tools\\mingw1310_64\\lib\\gcc\\x86_64-w64-mingw32\\13.1.0\\include\\c++\\x86_64-w64-mingw32","-isystem","D:\\qt\\Tools\\mingw1310_64\\lib\\gcc\\x86_64-w64-mingw32\\13.1.0\\include\\c++\\backward","-isystem","D:\\qt\\Tools\\QtCreator\\bin\\clang\\lib\\clang\\20\\include","-isystem","D:\\qt\\Tools\\mingw1310_64\\x86_64-w64-mingw32\\include","-fmessage-length=0","-fdiagnostics-show-note-include-stack","-fretain-comments-from-system-headers","-fmacro-backtrace-limit=0","-ferror-limit=1000","-x","c++-header","D:\\qt\\code\\dpautoexam\\SingleChoiceDialog.h"],"directory":"D:/qt/code/dpautoexam/build/Desktop_Qt_6_9_2_MinGW_64_bit-Debug/.qtc_clangd","file":"D:/qt/code/dpautoexam/SingleChoiceDialog.h"},{"arguments":["clang","-Wno-documentation-unknown-command","-Wno-unknown-warning-option","-Wno-unknown-pragmas","-nostdinc","-nostdinc++","-g","-std=gnu++1z","-Wall","-Wextra","-Wextra","-fexceptions","-mthreads","-fsyntax-only","-m64","--target=x86_64-w64-mingw32","-DUNICODE","-D_UNICODE","-DWIN32","-DMINGW_HAS_SECURE_API","-DQT_QML_DEBUG","-DQT_WIDGETS_LIB","-DQT_GUI_LIB","-DQT_CORE_LIB","-DQT_NEEDS_QMAIN","-DQ_CREATOR_RUN","-DQT_ANNOTATE_FUNCTION(x)=__attribute__((annotate(#x)))","-ID:\\qt\\Tools\\QtCreator\\share\\qtcreator\\cplusplus\\wrappedMingwHeaders","-ID:\\qt\\Tools\\QtCreator\\share\\qtcreator\\cplusplus\\wrappedQtHeaders","-ID:\\qt\\Tools\\QtCreator\\share\\qtcreator\\cplusplus\\wrappedQtHeaders\\QtCore","-ID:\\qt\\code\\dpautoexam","-ID:\\qt\\code\\dpautoexam\\third_party\\pugixml","-ID:\\qt\\6.9.2\\mingw_64\\include","-ID:\\qt\\6.9.2\\mingw_64\\include\\QtWidgets","-ID:\\qt\\6.9.2\\mingw_64\\include\\QtGui","-ID:\\qt\\6.9.2\\mingw_64\\include\\QtCore","-ID:\\qt\\code\\dpautoexam\\build\\Desktop_Qt_6_9_2_MinGW_64_bit-Debug\\debug","-ID:\\qt\\code\\dpautoexam\\build\\Desktop_Qt_6_9_2_MinGW_64_bit-Debug","-ID:\\qt\\6.9.2\\mingw_64\\mkspecs\\win32-g++","-isystem","D:\\qt\\Tools\\mingw1310_64\\lib\\gcc\\x86_64-w64-mingw32\\13.1.0\\include\\c++","-isystem","D:\\qt\\Tools\\mingw1310_64\\lib\\gcc\\x86_64-w64-mingw32\\13.1.0\\include\\c++\\x86_64-w64-mingw32","-isystem","D:\\qt\\Tools\\mingw1310_64\\lib\\gcc\\x86_64-w64-mingw32\\13.1.0\\include\\c++\\backward","-isystem","D:\\qt\\Tools\\QtCreator\\bin\\clang\\lib\\clang\\20\\include","-isystem","D:\\qt\\Tools\\mingw1310_64\\x86_64-w64-mingw32\\include","-fmessage-length=0","-fdiagnostics-show-note-include-stack","-fretain-comments-from-system-headers","-fmacro-backtrace-limit=0","-ferror-limit=1000","-x","c++-header","D:\\qt\\code\\dpautoexam\\SingleChoiceQuestion.h"],"directory":"D:/qt/code/dpautoexam/build/Desktop_Qt_6_9_2_MinGW_64_bit-Debug/.qtc_clangd","file":"D:/qt/code/dpautoexam/SingleChoiceQuestion.h"},{"arguments":["clang","-Wno-documentation-unknown-command","-Wno-unknown-warning-option","-Wno-unknown-pragmas","-nostdinc","-nostdinc++","-g","-std=gnu++1z","-Wall","-Wextra","-Wextra","-fexceptions","-mthreads","-fsyntax-only","-m64","--target=x86_64-w64-mingw32","-DUNICODE","-D_UNICODE","-DWIN32","-DMINGW_HAS_SECURE_API","-DQT_QML_DEBUG","-DQT_WIDGETS_LIB","-DQT_GUI_LIB","-DQT_CORE_LIB","-DQT_NEEDS_QMAIN","-DQ_CREATOR_RUN","-DQT_ANNOTATE_FUNCTION(x)=__attribute__((annotate(#x)))","-ID:\\qt\\Tools\\QtCreator\\share\\qtcreator\\cplusplus\\wrappedMingwHeaders","-ID:\\qt\\Tools\\QtCreator\\share\\qtcreator\\cplusplus\\wrappedQtHeaders","-ID:\\qt\\Tools\\QtCreator\\share\\qtcreator\\cplusplus\\wrappedQtHeaders\\QtCore","-ID:\\qt\\code\\dpautoexam","-ID:\\qt\\code\\dpautoexam\\third_party\\pugixml","-ID:\\qt\\6.9.2\\mingw_64\\include","-ID:\\qt\\6.9.2\\mingw_64\\include\\QtWidgets","-ID:\\qt\\6.9.2\\mingw_64\\include\\QtGui","-ID:\\qt\\6.9.2\\mingw_64\\include\\QtCore","-ID:\\qt\\code\\dpautoexam\\build\\Desktop_Qt_6_9_2_MinGW_64_bit-Debug\\debug","-ID:\\qt\\code\\dpautoexam\\build\\Desktop_Qt_6_9_2_MinGW_64_bit-Debug","-ID:\\qt\\6.9.2\\mingw_64\\mkspecs\\win32-g++","-isystem","D:\\qt\\Tools\\mingw1310_64\\lib\\gcc\\x86_64-w64-mingw32\\13.1.0\\include\\c++","-isystem","D:\\qt\\Tools\\mingw1310_64\\lib\\gcc\\x86_64-w64-mingw32\\13.1.0\\include\\c++\\x86_64-w64-mingw32","-isystem","D:\\qt\\Tools\\mingw1310_64\\lib\\gcc\\x86_64-w64-mingw32\\13.1.0\\include\\c++\\backward","-isystem","D:\\qt\\Tools\\QtCreator\\bin\\clang\\lib\\clang\\20\\include","-isystem","D:\\qt\\Tools\\mingw1310_64\\x86_64-w64-mingw32\\include","-fmessage-length=0","-fdiagnostics-show-note-include-stack","-fretain-comments-from-system-headers","-fmacro-backtrace-limit=0","-ferror-limit=1000","-x","c++-header","D:\\qt\\code\\dpautoexam\\XMLHandler.h"],"directory":"D:/qt/code/dpautoexam/build/Desktop_Qt_6_9_2_MinGW_64_bit-Debug/.qtc_clangd","file":"D:/qt/code/dpautoexam/XMLHandler.h"},{"arguments":["clang","-Wno-documentation-unknown-command","-Wno-unknown-warning-option","-Wno-unknown-pragmas","-nostdinc","-nostdinc++","-g","-std=gnu++1z","-Wall","-Wextra","-Wextra","-fexceptions","-mthreads","-fsyntax-only","-m64","--target=x86_64-w64-mingw32","-DUNICODE","-D_UNICODE","-DWIN32","-DMINGW_HAS_SECURE_API","-DQT_QML_DEBUG","-DQT_WIDGETS_LIB","-DQT_GUI_LIB","-DQT_CORE_LIB","-DQT_NEEDS_QMAIN","-DQ_CREATOR_RUN","-DQT_ANNOTATE_FUNCTION(x)=__attribute__((annotate(#x)))","-ID:\\qt\\Tools\\QtCreator\\share\\qtcreator\\cplusplus\\wrappedMingwHeaders","-ID:\\qt\\Tools\\QtCreator\\share\\qtcreator\\cplusplus\\wrappedQtHeaders","-ID:\\qt\\Tools\\QtCreator\\share\\qtcreator\\cplusplus\\wrappedQtHeaders\\QtCore","-ID:\\qt\\code\\dpautoexam","-ID:\\qt\\code\\dpautoexam\\third_party\\pugixml","-ID:\\qt\\6.9.2\\mingw_64\\include","-ID:\\qt\\6.9.2\\mingw_64\\include\\QtWidgets","-ID:\\qt\\6.9.2\\mingw_64\\include\\QtGui","-ID:\\qt\\6.9.2\\mingw_64\\include\\QtCore","-ID:\\qt\\code\\dpautoexam\\build\\Desktop_Qt_6_9_2_MinGW_64_bit-Debug\\debug","-ID:\\qt\\code\\dpautoexam\\build\\Desktop_Qt_6_9_2_MinGW_64_bit-Debug","-ID:\\qt\\6.9.2\\mingw_64\\mkspecs\\win32-g++","-isystem","D:\\qt\\Tools\\mingw1310_64\\lib\\gcc\\x86_64-w64-mingw32\\13.1.0\\include\\c++","-isystem","D:\\qt\\Tools\\mingw1310_64\\lib\\gcc\\x86_64-w64-mingw32\\13.1.0\\include\\c++\\x86_64-w64-mingw32","-isystem","D:\\qt\\Tools\\mingw1310_64\\lib\\gcc\\x86_64-w64-mingw32\\13.1.0\\include\\c++\\backward","-isystem","D:\\qt\\Tools\\QtCreator\\bin\\clang\\lib\\clang\\20\\include","-isystem","D:\\qt\\Tools\\mingw1310_64\\x86_64-w64-mingw32\\include","-fmessage-length=0","-fdiagnostics-show-note-include-stack","-fretain-comments-from-system-headers","-fmacro-backtrace-limit=0","-ferror-limit=1000","-x","c++-header","D:\\qt\\code\\dpautoexam\\mainwindow.h"],"directory":"D:/qt/code/dpautoexam/build/Desktop_Qt_6_9_2_MinGW_64_bit-Debug/.qtc_clangd","file":"D:/qt/code/dpautoexam/mainwindow.h"},{"arguments":["clang","-Wno-documentation-unknown-command","-Wno-unknown-warning-option","-Wno-unknown-pragmas","-nostdinc","-nostdinc++","-g","-std=gnu++1z","-Wall","-Wextra","-Wextra","-fexceptions","-mthreads","-fsyntax-only","-m64","--target=x86_64-w64-mingw32","-DUNICODE","-D_UNICODE","-DWIN32","-DMINGW_HAS_SECURE_API","-DQT_QML_DEBUG","-DQT_WIDGETS_LIB","-DQT_GUI_LIB","-DQT_CORE_LIB","-DQT_NEEDS_QMAIN","-DQ_CREATOR_RUN","-DQT_ANNOTATE_FUNCTION(x)=__attribute__((annotate(#x)))","-ID:\\qt\\Tools\\QtCreator\\share\\qtcreator\\cplusplus\\wrappedMingwHeaders","-ID:\\qt\\Tools\\QtCreator\\share\\qtcreator\\cplusplus\\wrappedQtHeaders","-ID:\\qt\\Tools\\QtCreator\\share\\qtcreator\\cplusplus\\wrappedQtHeaders\\QtCore","-ID:\\qt\\code\\dpautoexam","-ID:\\qt\\code\\dpautoexam\\third_party\\pugixml","-ID:\\qt\\6.9.2\\mingw_64\\include","-ID:\\qt\\6.9.2\\mingw_64\\include\\QtWidgets","-ID:\\qt\\6.9.2\\mingw_64\\include\\QtGui","-ID:\\qt\\6.9.2\\mingw_64\\include\\QtCore","-ID:\\qt\\code\\dpautoexam\\build\\Desktop_Qt_6_9_2_MinGW_64_bit-Debug\\debug","-ID:\\qt\\code\\dpautoexam\\build\\Desktop_Qt_6_9_2_MinGW_64_bit-Debug","-ID:\\qt\\6.9.2\\mingw_64\\mkspecs\\win32-g++","-isystem","D:\\qt\\Tools\\mingw1310_64\\lib\\gcc\\x86_64-w64-mingw32\\13.1.0\\include\\c++","-isystem","D:\\qt\\Tools\\mingw1310_64\\lib\\gcc\\x86_64-w64-mingw32\\13.1.0\\include\\c++\\x86_64-w64-mingw32","-isystem","D:\\qt\\Tools\\mingw1310_64\\lib\\gcc\\x86_64-w64-mingw32\\13.1.0\\include\\c++\\backward","-isystem","D:\\qt\\Tools\\QtCreator\\bin\\clang\\lib\\clang\\20\\include","-isystem","D:\\qt\\Tools\\mingw1310_64\\x86_64-w64-mingw32\\include","-fmessage-length=0","-fdiagnostics-show-note-include-stack","-fretain-comments-from-system-headers","-fmacro-backtrace-limit=0","-ferror-limit=1000","-x","c++-header","D:\\qt\\code\\dpautoexam\\build\\Desktop_Qt_6_9_2_MinGW_64_bit-Debug\\ui_EssayDialog.h"],"directory":"D:/qt/code/dpautoexam/build/Desktop_Qt_6_9_2_MinGW_64_bit-Debug/.qtc_clangd","file":"D:/qt/code/dpautoexam/build/Desktop_Qt_6_9_2_MinGW_64_bit-Debug/ui_EssayDialog.h"},{"arguments":["clang","-Wno-documentation-unknown-command","-Wno-unknown-warning-option","-Wno-unknown-pragmas","-nostdinc","-nostdinc++","-g","-std=gnu++1z","-Wall","-Wextra","-Wextra","-fexceptions","-mthreads","-fsyntax-only","-m64","--target=x86_64-w64-mingw32","-DUNICODE","-D_UNICODE","-DWIN32","-DMINGW_HAS_SECURE_API","-DQT_QML_DEBUG","-DQT_WIDGETS_LIB","-DQT_GUI_LIB","-DQT_CORE_LIB","-DQT_NEEDS_QMAIN","-DQ_CREATOR_RUN","-DQT_ANNOTATE_FUNCTION(x)=__attribute__((annotate(#x)))","-ID:\\qt\\Tools\\QtCreator\\share\\qtcreator\\cplusplus\\wrappedMingwHeaders","-ID:\\qt\\Tools\\QtCreator\\share\\qtcreator\\cplusplus\\wrappedQtHeaders","-ID:\\qt\\Tools\\QtCreator\\share\\qtcreator\\cplusplus\\wrappedQtHeaders\\QtCore","-ID:\\qt\\code\\dpautoexam","-ID:\\qt\\code\\dpautoexam\\third_party\\pugixml","-ID:\\qt\\6.9.2\\mingw_64\\include","-ID:\\qt\\6.9.2\\mingw_64\\include\\QtWidgets","-ID:\\qt\\6.9.2\\mingw_64\\include\\QtGui","-ID:\\qt\\6.9.2\\mingw_64\\include\\QtCore","-ID:\\qt\\code\\dpautoexam\\build\\Desktop_Qt_6_9_2_MinGW_64_bit-Debug\\debug","-ID:\\qt\\code\\dpautoexam\\build\\Desktop_Qt_6_9_2_MinGW_64_bit-Debug","-ID:\\qt\\6.9.2\\mingw_64\\mkspecs\\win32-g++","-isystem","D:\\qt\\Tools\\mingw1310_64\\lib\\gcc\\x86_64-w64-mingw32\\13.1.0\\include\\c++","-isystem","D:\\qt\\Tools\\mingw1310_64\\lib\\gcc\\x86_64-w64-mingw32\\13.1.0\\include\\c++\\x86_64-w64-mingw32","-isystem","D:\\qt\\Tools\\mingw1310_64\\lib\\gcc\\x86_64-w64-mingw32\\13.1.0\\include\\c++\\backward","-isystem","D:\\qt\\Tools\\QtCreator\\bin\\clang\\lib\\clang\\20\\include","-isystem","D:\\qt\\Tools\\mingw1310_64\\x86_64-w64-mingw32\\include","-fmessage-length=0","-fdiagnostics-show-note-include-stack","-fretain-comments-from-system-headers","-fmacro-backtrace-limit=0","-ferror-limit=1000","-x","c++-header","D:\\qt\\code\\dpautoexam\\build\\Desktop_Qt_6_9_2_MinGW_64_bit-Debug\\ui_JudgementDialog.h"],"directory":"D:/qt/code/dpautoexam/build/Desktop_Qt_6_9_2_MinGW_64_bit-Debug/.qtc_clangd","file":"D:/qt/code/dpautoexam/build/Desktop_Qt_6_9_2_MinGW_64_bit-Debug/ui_JudgementDialog.h"},{"arguments":["clang","-Wno-documentation-unknown-command","-Wno-unknown-warning-option","-Wno-unknown-pragmas","-nostdinc","-nostdinc++","-g","-std=gnu++1z","-Wall","-Wextra","-Wextra","-fexceptions","-mthreads","-fsyntax-only","-m64","--target=x86_64-w64-mingw32","-DUNICODE","-D_UNICODE","-DWIN32","-DMINGW_HAS_SECURE_API","-DQT_QML_DEBUG","-DQT_WIDGETS_LIB","-DQT_GUI_LIB","-DQT_CORE_LIB","-DQT_NEEDS_QMAIN","-DQ_CREATOR_RUN","-DQT_ANNOTATE_FUNCTION(x)=__attribute__((annotate(#x)))","-ID:\\qt\\Tools\\QtCreator\\share\\qtcreator\\cplusplus\\wrappedMingwHeaders","-ID:\\qt\\Tools\\QtCreator\\share\\qtcreator\\cplusplus\\wrappedQtHeaders","-ID:\\qt\\Tools\\QtCreator\\share\\qtcreator\\cplusplus\\wrappedQtHeaders\\QtCore","-ID:\\qt\\code\\dpautoexam","-ID:\\qt\\code\\dpautoexam\\third_party\\pugixml","-ID:\\qt\\6.9.2\\mingw_64\\include","-ID:\\qt\\6.9.2\\mingw_64\\include\\QtWidgets","-ID:\\qt\\6.9.2\\mingw_64\\include\\QtGui","-ID:\\qt\\6.9.2\\mingw_64\\include\\QtCore","-ID:\\qt\\code\\dpautoexam\\build\\Desktop_Qt_6_9_2_MinGW_64_bit-Debug\\debug","-ID:\\qt\\code\\dpautoexam\\build\\Desktop_Qt_6_9_2_MinGW_64_bit-Debug","-ID:\\qt\\6.9.2\\mingw_64\\mkspecs\\win32-g++","-isystem","D:\\qt\\Tools\\mingw1310_64\\lib\\gcc\\x86_64-w64-mingw32\\13.1.0\\include\\c++","-isystem","D:\\qt\\Tools\\mingw1310_64\\lib\\gcc\\x86_64-w64-mingw32\\13.1.0\\include\\c++\\x86_64-w64-mingw32","-isystem","D:\\qt\\Tools\\mingw1310_64\\lib\\gcc\\x86_64-w64-mingw32\\13.1.0\\include\\c++\\backward","-isystem","D:\\qt\\Tools\\QtCreator\\bin\\clang\\lib\\clang\\20\\include","-isystem","D:\\qt\\Tools\\mingw1310_64\\x86_64-w64-mingw32\\include","-fmessage-length=0","-fdiagnostics-show-note-include-stack","-fretain-comments-from-system-headers","-fmacro-backtrace-limit=0","-ferror-limit=1000","-x","c++-header","D:\\qt\\code\\dpautoexam\\build\\Desktop_Qt_6_9_2_MinGW_64_bit-Debug\\ui_SingleChoiceDialog.h"],"directory":"D:/qt/code/dpautoexam/build/Desktop_Qt_6_9_2_MinGW_64_bit-Debug/.qtc_clangd","file":"D:/qt/code/dpautoexam/build/Desktop_Qt_6_9_2_MinGW_64_bit-Debug/ui_SingleChoiceDialog.h"},{"arguments":["clang","-Wno-documentation-unknown-command","-Wno-unknown-warning-option","-Wno-unknown-pragmas","-nostdinc","-nostdinc++","-g","-std=gnu++1z","-Wall","-Wextra","-Wextra","-fexceptions","-mthreads","-fsyntax-only","-m64","--target=x86_64-w64-mingw32","-DUNICODE","-D_UNICODE","-DWIN32","-DMINGW_HAS_SECURE_API","-DQT_QML_DEBUG","-DQT_WIDGETS_LIB","-DQT_GUI_LIB","-DQT_CORE_LIB","-DQT_NEEDS_QMAIN","-DQ_CREATOR_RUN","-DQT_ANNOTATE_FUNCTION(x)=__attribute__((annotate(#x)))","-ID:\\qt\\Tools\\QtCreator\\share\\qtcreator\\cplusplus\\wrappedMingwHeaders","-ID:\\qt\\Tools\\QtCreator\\share\\qtcreator\\cplusplus\\wrappedQtHeaders","-ID:\\qt\\Tools\\QtCreator\\share\\qtcreator\\cplusplus\\wrappedQtHeaders\\QtCore","-ID:\\qt\\code\\dpautoexam","-ID:\\qt\\code\\dpautoexam\\third_party\\pugixml","-ID:\\qt\\6.9.2\\mingw_64\\include","-ID:\\qt\\6.9.2\\mingw_64\\include\\QtWidgets","-ID:\\qt\\6.9.2\\mingw_64\\include\\QtGui","-ID:\\qt\\6.9.2\\mingw_64\\include\\QtCore","-ID:\\qt\\code\\dpautoexam\\build\\Desktop_Qt_6_9_2_MinGW_64_bit-Debug\\debug","-ID:\\qt\\code\\dpautoexam\\build\\Desktop_Qt_6_9_2_MinGW_64_bit-Debug","-ID:\\qt\\6.9.2\\mingw_64\\mkspecs\\win32-g++","-isystem","D:\\qt\\Tools\\mingw1310_64\\lib\\gcc\\x86_64-w64-mingw32\\13.1.0\\include\\c++","-isystem","D:\\qt\\Tools\\mingw1310_64\\lib\\gcc\\x86_64-w64-mingw32\\13.1.0\\include\\c++\\x86_64-w64-mingw32","-isystem","D:\\qt\\Tools\\mingw1310_64\\lib\\gcc\\x86_64-w64-mingw32\\13.1.0\\include\\c++\\backward","-isystem","D:\\qt\\Tools\\QtCreator\\bin\\clang\\lib\\clang\\20\\include","-isystem","D:\\qt\\Tools\\mingw1310_64\\x86_64-w64-mingw32\\include","-fmessage-length=0","-fdiagnostics-show-note-include-stack","-fretain-comments-from-system-headers","-fmacro-backtrace-limit=0","-ferror-limit=1000","-x","c++-header","D:\\qt\\code\\dpautoexam\\build\\Desktop_Qt_6_9_2_MinGW_64_bit-Debug\\ui_MultipleChoiceDialog.h"],"directory":"D:/qt/code/dpautoexam/build/Desktop_Qt_6_9_2_MinGW_64_bit-Debug/.qtc_clangd","file":"D:/qt/code/dpautoexam/build/Desktop_Qt_6_9_2_MinGW_64_bit-Debug/ui_MultipleChoiceDialog.h"},{"arguments":["clang","-Wno-documentation-unknown-command","-Wno-unknown-warning-option","-Wno-unknown-pragmas","-nostdinc","-nostdinc++","-g","-std=gnu++1z","-Wall","-Wextra","-Wextra","-fexceptions","-mthreads","-fsyntax-only","-m64","--target=x86_64-w64-mingw32","-DUNICODE","-D_UNICODE","-DWIN32","-DMINGW_HAS_SECURE_API","-DQT_QML_DEBUG","-DQT_WIDGETS_LIB","-DQT_GUI_LIB","-DQT_CORE_LIB","-DQT_NEEDS_QMAIN","-DQ_CREATOR_RUN","-DQT_ANNOTATE_FUNCTION(x)=__attribute__((annotate(#x)))","-ID:\\qt\\Tools\\QtCreator\\share\\qtcreator\\cplusplus\\wrappedMingwHeaders","-ID:\\qt\\Tools\\QtCreator\\share\\qtcreator\\cplusplus\\wrappedQtHeaders","-ID:\\qt\\Tools\\QtCreator\\share\\qtcreator\\cplusplus\\wrappedQtHeaders\\QtCore","-ID:\\qt\\code\\dpautoexam","-ID:\\qt\\code\\dpautoexam\\third_party\\pugixml","-ID:\\qt\\6.9.2\\mingw_64\\include","-ID:\\qt\\6.9.2\\mingw_64\\include\\QtWidgets","-ID:\\qt\\6.9.2\\mingw_64\\include\\QtGui","-ID:\\qt\\6.9.2\\mingw_64\\include\\QtCore","-ID:\\qt\\code\\dpautoexam\\build\\Desktop_Qt_6_9_2_MinGW_64_bit-Debug\\debug","-ID:\\qt\\code\\dpautoexam\\build\\Desktop_Qt_6_9_2_MinGW_64_bit-Debug","-ID:\\qt\\6.9.2\\mingw_64\\mkspecs\\win32-g++","-isystem","D:\\qt\\Tools\\mingw1310_64\\lib\\gcc\\x86_64-w64-mingw32\\13.1.0\\include\\c++","-isystem","D:\\qt\\Tools\\mingw1310_64\\lib\\gcc\\x86_64-w64-mingw32\\13.1.0\\include\\c++\\x86_64-w64-mingw32","-isystem","D:\\qt\\Tools\\mingw1310_64\\lib\\gcc\\x86_64-w64-mingw32\\13.1.0\\include\\c++\\backward","-isystem","D:\\qt\\Tools\\QtCreator\\bin\\clang\\lib\\clang\\20\\include","-isystem","D:\\qt\\Tools\\mingw1310_64\\x86_64-w64-mingw32\\include","-fmessage-length=0","-fdiagnostics-show-note-include-stack","-fretain-comments-from-system-headers","-fmacro-backtrace-limit=0","-ferror-limit=1000","-x","c++-header","D:\\qt\\code\\dpautoexam\\build\\Desktop_Qt_6_9_2_MinGW_64_bit-Debug\\ui_mainwindow.h"],"directory":"D:/qt/code/dpautoexam/build/Desktop_Qt_6_9_2_MinGW_64_bit-Debug/.qtc_clangd","file":"D:/qt/code/dpautoexam/build/Desktop_Qt_6_9_2_MinGW_64_bit-Debug/ui_mainwindow.h"},{"arguments":["clang","-Wno-documentation-unknown-command","-Wno-unknown-warning-option","-Wno-unknown-pragmas","-nostdinc","-nostdinc++","-g","-std=gnu++1z","-Wall","-Wextra","-Wextra","-fexceptions","-mthreads","-fsyntax-only","-m64","--target=x86_64-w64-mingw32","-DUNICODE","-D_UNICODE","-DWIN32","-DMINGW_HAS_SECURE_API","-DQT_QML_DEBUG","-DQT_WIDGETS_LIB","-DQT_GUI_LIB","-DQT_CORE_LIB","-DQT_NEEDS_QMAIN","-DQ_CREATOR_RUN","-DQT_ANNOTATE_FUNCTION(x)=__attribute__((annotate(#x)))","-ID:\\qt\\Tools\\QtCreator\\share\\qtcreator\\cplusplus\\wrappedMingwHeaders","-ID:\\qt\\Tools\\QtCreator\\share\\qtcreator\\cplusplus\\wrappedQtHeaders","-ID:\\qt\\Tools\\QtCreator\\share\\qtcreator\\cplusplus\\wrappedQtHeaders\\QtCore","-ID:\\qt\\code\\dpautoexam","-ID:\\qt\\code\\dpautoexam\\third_party\\pugixml","-ID:\\qt\\6.9.2\\mingw_64\\include","-ID:\\qt\\6.9.2\\mingw_64\\include\\QtWidgets","-ID:\\qt\\6.9.2\\mingw_64\\include\\QtGui","-ID:\\qt\\6.9.2\\mingw_64\\include\\QtCore","-ID:\\qt\\code\\dpautoexam\\build\\Desktop_Qt_6_9_2_MinGW_64_bit-Debug\\debug","-ID:\\qt\\code\\dpautoexam\\build\\Desktop_Qt_6_9_2_MinGW_64_bit-Debug","-ID:\\qt\\6.9.2\\mingw_64\\mkspecs\\win32-g++","-isystem","D:\\qt\\Tools\\mingw1310_64\\lib\\gcc\\x86_64-w64-mingw32\\13.1.0\\include\\c++","-isystem","D:\\qt\\Tools\\mingw1310_64\\lib\\gcc\\x86_64-w64-mingw32\\13.1.0\\include\\c++\\x86_64-w64-mingw32","-isystem","D:\\qt\\Tools\\mingw1310_64\\lib\\gcc\\x86_64-w64-mingw32\\13.1.0\\include\\c++\\backward","-isystem","D:\\qt\\Tools\\QtCreator\\bin\\clang\\lib\\clang\\20\\include","-isystem","D:\\qt\\Tools\\mingw1310_64\\x86_64-w64-mingw32\\include","-fmessage-length=0","-fdiagnostics-show-note-include-stack","-fretain-comments-from-system-headers","-fmacro-backtrace-limit=0","-ferror-limit=1000","-x","c++-header","D:\\qt\\code\\dpautoexam\\build\\Desktop_Qt_6_9_2_MinGW_64_bit-Debug\\ui_ExamDialog.h"],"directory":"D:/qt/code/dpautoexam/build/Desktop_Qt_6_9_2_MinGW_64_bit-Debug/.qtc_clangd","file":"D:/qt/code/dpautoexam/build/Desktop_Qt_6_9_2_MinGW_64_bit-Debug/ui_ExamDialog.h"}]